[
    {
        "text": "حدد رئيس الوزراء البريطاني ديفيد كاميرون، اليوم (الاثنين)، ملامح استراتيجية للتصدي للتطرف داخل بريطانيا؛ وهي مسألة اعتبرها كاميرون \"صراع جيلنا\"، متعهدا خلال خطابه في مدينة بيرمنغهام بالتصدي لهؤلاء الذين ينشرون التطرف بين الشبان المسلمين البريطانيين.\n\n ورسم كاميرون الاطار العام لاستراتيجية مكافحة التطرف التي المقرر ان تنشر كاملة في وقت لاحق هذا العام، والتي تسعى للتصدي لانتشار الأفكار المتطرفة التي يروج لها متشددو تنظيم \"داعش\".\n\n وحسبما تناقلت وسائل الإعلام البريطانية، فإن خطة رئيس الوزراء ستكون على مدى خمسة أعوام للقضاء على التطرف الداخلي من خلال أربعة محاور، وهي: القضاء على إيديولوجية التطرف، والوقوف في وجه عمليات التجنيد وغسل الأدمغة بالأفكار المتطرفة، وإعادة اصوات الاسلام المعتدل إلى المجتمع البريطاني، والتعامل مع أزمات الهوية التي يواجهها بعض المسلمين المولودين في بريطانيا.\n\n وسيكون من الأهداف الرئيسية للاستراتيجية مكافحة صعود من يطلق عليهم اسم \"متطرفي الداخل\"، وهو أمر يقول كاميرون انه لا يمكن عمله دون فهم الاسباب التي تجتذب الناس لـ\"داعش\" والتصدي لها. إذ قال كاميرون في سياق خطابه، \"عندما تسعى مجموعات متطرفة مثل داعش لحشد شبابنا لقضيتها المسمومة، فانها قد تمنحهم احساسا بالانتماء ربما يفتقرون اليه هنا في الداخل\"، واستطرد بقوله \"هذا الامر يجعلهم أكثر عرضة للتطرف\".\n\n كما أكد رئيس الوزراء البريطاني أن المجتمع البريطاني \"مجتمع ديمقراطي متعدد الأعراق والأديان\"، مضيفا أن \"هذا المجتمع يحتوى جميع مواطنيه\". ونوه بأنه سيعمل مع المسلمين داخل البلاد لمحاربة أفكار التطرف.\n\n وتضمنت استراتيجية الحكومة البريطانية مقترحات للقضاء على التطرف من خلال المحاور الأربعة المشار إليها في الأعلى وأهمها: إعطاء الصلاحية لأهالي الشباب الذين يبدون قابلية بالسفر إلى سوريا بإتلاف جوازات سفرهم، وتحفيز زيادة الاندماج في المدارس، والتطرق للتجنيد والتطرف داخل السجون وعلى شبكة الانترنت، ورصد القنوات التي تبث رسائل متطرفة وحظرها، وزيادة صلاحيات الحكومة في توقيف جماعات داخل البلاد تنشر الفكر المتطرف أو تحاول التجنيد، والاستثمار بجمعيات تحارب الفكر المتطرف عن طريق نشر الاسلام المتعدل، وتأسيس منتدى تفاعلي لمخاطبة ظاهرة التطرف وانتشارها في بريطانيا، وإعادة هيكلة آلية توزيع السكن لتفادي عزل أو انفصال المسل",
        "entities": {
            "PERS": [
                "ديفيد كاميرون",
                "كام",
                "يرون"
            ],
            "LOC": [
                "بريطانيا",
                "بيرمنغهام",
                "سوريا",
                "الولايات المتحدة",
                "بالعراق",
                "والعراق"
            ],
            "ORG": [
                "داعش"
            ],
            "MISC": [
                "الاسلام"
            ]
        },
        "labeled_entities": [
            {
                "entity": "ديفيد كاميرون",
                "label": "Protagonist"
            },
            {
                "entity": "بريطانيا",
                "label": "Neutral"
            },
            {
                "entity": "بيرمنغهام",
                "label": "Neutral"
            },
            {
                "entity": "سوريا",
                "label": "Neutral"
            },
            {
                "entity": "الولايات المتحدة",
                "label": "Neutral"
            },
            {
                "entity": "بالعراق",
                "label": "Neutral"
            },
            {
                "entity": "والعراق",
                "label": "Neutral"
            },
            {
                "entity": "داعش",
                "label": "Antagonist"
            },
            {
                "entity": "الاسلام",
                "label": "Neutral"
            }
        ],
        "events": [
            {
                "subject": "ديفيد كاميرون",
                "action": "حدد",
                "object": "ملامح استراتيجية",
                "context": "للتصدي للتطرف داخل بريطانيا",
                "subject_role": "Protagonist",
                "object_role": "Unknown"
            },
            {
                "subject": "كاميرون",
                "action": "تعهد",
                "object": "التصدي",
                "context": "لهؤلاء الذين ينشرون التطرف بين الشبان المسلمين البريطانيين",
                "subject_role": "Protagonist",
                "object_role": "Unknown"
            },
            {
                "subject": "كاميرون",
                "action": "رسم",
                "object": "الاطار العام",
                "context": "لاستراتيجية مكافحة التطرف",
                "subject_role": "Protagonist",
                "object_role": "Neutral"
            },
            {
                "subject": "الاستراتيجية",
                "action": "تسعى",
                "object": "التصدي",
                "context": "لانتشار الأفكار المتطرفة التي يروج لها متشددو تنظيم داعش",
                "subject_role": "Unknown",
                "object_role": "Unknown"
            },
            {
                "subject": "خطة رئيس الوزراء",
                "action": "ستكون",
                "object": "القضاء",
                "context": "على التطرف الداخلي من خلال أربعة محاور",
                "subject_role": "Unknown",
                "object_role": "Unknown"
            },
            {
                "subject": "الخطة",
                "action": "تتضمن",
                "object": "القضاء على ايديولوجية التطرف",
                "context": null,
                "subject_role": "Unknown",
                "object_role": "Unknown"
            },
            {
                "subject": "الخطة",
                "action": "تتضمن",
                "object": "الوقوف",
                "context": "في وجه عمليات التجنيد وغسل الأدمغة بالأفكار المتطرفة",
                "subject_role": "Unknown",
                "object_role": "Unknown"
            },
            {
                "subject": "الخطة",
                "action": "تتضمن",
                "object": "إعادة اصوات الاسلام المعتدل",
                "context": "إلى المجتمع البريطاني",
                "subject_role": "Unknown",
                "object_role": "Unknown"
            },
            {
                "subject": "الخطة",
                "action": "تتضمن",
                "object": "التعامل",
                "context": "مع أزمات الهوية التي يواجهها بعض المسلمين المولودين في بريطانيا",
                "subject_role": "Unknown",
                "object_role": "Unknown"
            },
            {
                "subject": "الاستراتيجية",
                "action": "ستكون",
                "object": "مكافحة",
                "context": "صعود من يطلق عليهم اسم متطرفي الداخل",
                "subject_role": "Unknown",
                "object_role": "Unknown"
            },
            {
                "subject": "كاميرون",
                "action": "قال",
                "object": "تسعى مجموعات متطرفة",
                "context": "مثل داعش لحشد شبابنا لقضيتها المسمومة",
                "subject_role": "Protagonist",
                "object_role": "Unknown"
            },
            {
                "subject": "كاميرون",
                "action": "أكد",
                "object": "يحتوى المجتمع",
                "context": "جميع مواطنيه",
                "subject_role": "Protagonist",
                "object_role": "Unknown"
            },
            {
                "subject": "كاميرون",
                "action": "نوه",
                "object": "سيعمل",
                "context": "مع المسلمين داخل البلاد لمحاربة أفكار التطرف",
                "subject_role": "Protagonist",
                "object_role": "Unknown"
            },
            {
                "subject": "استراتيجية الحكومة البريطانية",
                "action": "تضمنت",
                "object": "مقترحات",
                "context": "للقضاء على التطرف من خلال المحاور الأربعة المشار إليها",
                "subject_role": "Unknown",
                "object_role": "Unknown"
            },
            {
                "subject": "الاستراتيجية",
                "action": "تضمنت",
                "object": "إعطاء الصلاحية",
                "context": "لأهالي الشباب الذين يبدون قابلية بالسفر إلى سوريا بإتلاف جوازات سفرهم",
                "subject_role": "Unknown",
                "object_role": "Unknown"
            },
            {
                "subject": "الاستراتيجية",
                "action": "تضمنت",
                "object": "تحفيز زيادة الاندماج",
                "context": "في المدارس",
                "subject_role": "Unknown",
                "object_role": "Unknown"
            },
            {
                "subject": "الاستراتيجية",
                "action": "تضمنت",
                "object": "التطرق للتجنيد والتطرف",
                "context": "داخل السجون وعلى شبكة الانترنت",
                "subject_role": "Unknown",
                "object_role": "Unknown"
            },
            {
                "subject": "الاستراتيجية",
                "action": "تضمنت",
                "object": "رصد القنوات",
                "context": "التي تبث رسائل متطرفة وحظرها",
                "subject_role": "Unknown",
                "object_role": "Unknown"
            },
            {
                "subject": "الاستراتيجية",
                "action": "تضمنت",
                "object": "زيادة صلاحيات الحكومة",
                "context": "في توقيف جماعات داخل البلاد تنشر الفكر المتطرف أو تحاول التجنيد",
                "subject_role": "Unknown",
                "object_role": "Unknown"
            },
            {
                "subject": "الاستراتيجية",
                "action": "تضمنت",
                "object": "الاستثمار بجمعيات",
                "context": "تحارب الفكر المتطرف عن طريق نشر الاسلام المتعدل",
                "subject_role": "Unknown",
                "object_role": "Unknown"
            },
            {
                "subject": "الاستراتيجية",
                "action": "تضمنت",
                "object": "تأسيس منتدى تفاعلي",
                "context": "لمخاطبة ظاهرة التطرف وانتشارها في بريطانيا",
                "subject_role": "Unknown",
                "object_role": "Unknown"
            },
            {
                "subject": "الاستراتيجية",
                "action": "تضمنت",
                "object": "إعادة هيكلة آلية توزيع السكن",
                "context": "لتفادي عزل أو انفصال المسل",
                "subject_role": "Unknown",
                "object_role": "Unknown"
            }
        ]
    },
    {
        "text": "أصدر الرئيس عبدربه منصور هادي رئيس الجمهورية اليمنية، اليوم (الاثنين)، قراراً جمهورياً بتعيين نايف البكري محافظا لعدن، وذلك بعد الانتصارات التي حققتها قوات المقاومة الشعبية في طرد المتمردين الحوثيين من المدينة.\n\n نايف البكري شغل منصب وكيل محافظة عدن لشؤون المديريات من قبل، وله علاقات جيدة مع مختلف القوى السياسية في المدينة، ويعتبر الرجل الأول.\n\n من جهة أخرى، أعلن بدر محمد باسملة وزير النقل اليمني عن إعداد خطة طوارئ للمدينة، مؤكدا أن أولوية الحكومة تشغيل الموانئ وتحسين الخدمات. موضحا ان فريقاً فنياً متخصصاً وصل من الإمارات لإعادة تشغيل المطار خلال أربع وعشرين ساعة واستئناف الرحلات من وإلى عدن خلال الساعات المقبلة. داعيا المنظمات الحقوقية والاعلاميين للقدومِ الى عدن لرصد المآسي التي ارتكبها المتمردون، مؤكداً ان الحكومة ستؤمن لهم رحلات من أي مطار في العالم.\n\n من جانبه، قال المتحدث الرسمي باسم الحكومة اليمنية راجح بادي، إن حجم الدمار في عدن لم يكن متوقعاً، لا سيما الذي طال البنى التحتية؛ فمطار عدن على سبيل المثال، مدمر بشكل شبه كامل، ومحطات توليد الكهرباء والمنشآت النفطية تعرضت هي الأخرى أكثر من مرة للقصف من قبل الحوثيين، حيث كانوا حينها يريدون الضغط على المقاومة الشعبية من خلال منعها من الحصول على المحروقات. وهو ما لم ينجحوا فيه. مبينا انه سيحتاج إعادة تأهيلها لمبالغ كبيرة وأشهر من العمل.",
        "entities": {
            "PERS": [
                "عبدربه منصور هادي",
                "نايف البكري",
                "بدر محمد باسملة",
                "راجح بادي"
            ],
            "LOC": [
                "لعد",
                "ن",
                "عدن",
                "الإمارات"
            ],
            "ORG": [
                "الحوثيين"
            ]
        },
        "labeled_entities": [
            {
                "entity": "عبدربه منصور هادي",
                "label": "Neutral"
            },
            {
                "entity": "نايف البكري",
                "label": "Protagonist"
            },
            {
                "entity": "بدر محمد باسملة",
                "label": "Neutral"
            },
            {
                "entity": "راجح بادي",
                "label": "Neutral"
            },
            {
                "entity": "لعد",
                "label": "Neutral"
            },
            {
                "entity": "ن",
                "label": "Neutral"
            },
            {
                "entity": "عدن",
                "label": "Neutral"
            },
            {
                "entity": "الإمارات",
                "label": "Neutral"
            },
            {
                "entity": "الحوثيين",
                "label": "Antagonist"
            }
        ],
        "events": [
            {
                "subject": "عبدربه منصور هادي",
                "action": "أصدر",
                "object": "قراراً جمهورياً",
                "context": "بتعيين نايف البكري محافظا لعدن",
                "subject_role": "Neutral",
                "object_role": "Unknown"
            },
            {
                "subject": "نايف البكري",
                "action": "عين",
                "object": "محافظا لعدن",
                "context": "بعد الانتصارات التي حققتها قوات المقاومة الشعبية في طرد الحوثيين من عدن",
                "subject_role": "Protagonist",
                "object_role": "Unknown"
            },
            {
                "subject": "نايف البكري",
                "action": "شغل",
                "object": "منصب وكيل محافظة عدن",
                "context": "لشؤون المديريات من قبل",
                "subject_role": "Protagonist",
                "object_role": "Unknown"
            },
            {
                "subject": "بدر محمد باسملة",
                "action": "أعلن",
                "object": "خطة طوارئ",
                "context": "للمدينة",
                "subject_role": "Neutral",
                "object_role": "Unknown"
            },
            {
                "subject": "الحكومة",
                "action": "ستشغل",
                "object": "الموانئ",
                "context": "وتحسن الخدمات",
                "subject_role": "Unknown",
                "object_role": "Unknown"
            },
            {
                "subject": "فريقاً فنياً متخصصاً",
                "action": "وصل",
                "object": null,
                "context": "من الإمارات لإعادة تشغيل المطار",
                "subject_role": "Unknown",
                "object_role": "Unknown"
            },
            {
                "subject": "فريقاً فنياً متخصصاً",
                "action": "أعاد",
                "object": "تشغيل المطار",
                "context": "خلال أربع وعشرين ساعة",
                "subject_role": "Unknown",
                "object_role": "Unknown"
            },
            {
                "subject": "فريقاً فنياً متخصصاً",
                "action": "استأنف",
                "object": "الرحلات",
                "context": "من وإلى عدن خلال الساعات المقبلة",
                "subject_role": "Unknown",
                "object_role": "Neutral"
            },
            {
                "subject": "بدر محمد باسملة",
                "action": "دعا",
                "object": "المنظمات الحقوقية والاعلاميين",
                "context": "للقدومِ الى عدن لرصد المآسي التي ارتكبها المتمردون",
                "subject_role": "Neutral",
                "object_role": "Unknown"
            },
            {
                "subject": "الحكومة",
                "action": "ستؤمن",
                "object": "رحلات",
                "context": "للمنظمات الحقوقية والاعلاميين من أي مطار في العالم",
                "subject_role": "Unknown",
                "object_role": "Unknown"
            },
            {
                "subject": "راجح بادي",
                "action": "قال",
                "object": null,
                "context": "إن حجم الدمار في عدن لم يكن متوقعاً",
                "subject_role": "Neutral",
                "object_role": "Unknown"
            },
            {
                "subject": "مطار عدن",
                "action": "دمر",
                "object": null,
                "context": "بشكل شبه كامل",
                "subject_role": "Unknown",
                "object_role": "Unknown"
            },
            {
                "subject": "الحوثيين",
                "action": "قصفوا",
                "object": "محطات توليد الكهرباء والمنشآت النفطية",
                "context": "أكثر من مرة",
                "subject_role": "Antagonist",
                "object_role": "Unknown"
            },
            {
                "subject": "الحوثيين",
                "action": "أرادوا",
                "object": "الضغط على المقاومة الشعبية",
                "context": "من خلال منعها من الحصول على المحروقات",
                "subject_role": "Antagonist",
                "object_role": "Unknown"
            },
            {
                "subject": "إعادة تأهيلها",
                "action": "سيحتاج",
                "object": "مبالغ كبيرة",
                "context": "وأشهر من العمل",
                "subject_role": "Unknown",
                "object_role": "Unknown"
            }
        ]
    },
    {
        "text": "وافق مجلس الأمن الدولي، اليوم (الاثنين)، على اتفاق يحد من برنامج ايران النووي مقابل تخفيف العقوبات على طهران، لكن سيكون بامكان معاودة فرض عقوبات الامم المتحدة خلال العقد المقبل اذا انتهكت إيران الاتفاق التاريخي.\n\n ووافق المجلس المؤلف من 15 دولة على قرار جرى التفاوض عليه في اطار الاتفاق الذي أبرم في فيينا الاسبوع الماضي بين ايران والقوى الست الدولية.\n\n وفي تطور لاحق، نقلت وكالة تسنيم الايرانية للانباء عن محمد علي جعفري قائد الحرس الثوري الايراني، قوله ان قرار مجلس الامن الدولي الذي جرى تمريره اليوم، ويقر الاتفاق النووي الايراني غير مقبول. مضيفا \"قبل وقت قصير من تمرير القرار في نيويورك، بعض أجزاء المسودة تجاوزت بوضوح الخطوط الحمراء لإيران، خاصة ما يتعلق بقدرات ايران العسكرية ولن نقبله أبدا\".",
        "entities": {
            "ORG": [
                "مجلس الأمن الدولي",
                "الامم المتحدة",
                "تسنيم",
                "الحرس",
                "مجلس الامن الدولي"
            ],
            "LOC": [
                "ايران",
                "طهران",
                "إيران",
                "فيينا",
                "نيويورك",
                "لإ",
                "يران"
            ],
            "PERS": [
                "محمد علي جعفري"
            ]
        },
        "labeled_entities": [
            {
                "entity": "مجلس الأمن الدولي",
                "label": "Neutral"
            },
            {
                "entity": "الامم المتحدة",
                "label": "Neutral"
            },
            {
                "entity": "تسنيم",
                "label": "Neutral"
            },
            {
                "entity": "الحرس",
                "label": "Antagonist"
            },
            {
                "entity": "مجلس الامن الدولي",
                "label": "Neutral"
            },
            {
                "entity": "ايران",
                "label": "Protagonist"
            },
            {
                "entity": "طهران",
                "label": "Protagonist"
            },
            {
                "entity": "إيران",
                "label": "Protagonist"
            },
            {
                "entity": "فيينا",
                "label": "Neutral"
            },
            {
                "entity": "نيويورك",
                "label": "Neutral"
            },
            {
                "entity": "لإ",
                "label": "Neutral"
            },
            {
                "entity": "يران",
                "label": "Protagonist"
            },
            {
                "entity": "محمد علي جعفري",
                "label": "Antagonist"
            }
        ],
        "events": [
            {
                "subject": "مجلس الأمن الدولي",
                "action": "وافق",
                "object": "اتفاق",
                "context": "يحد من برنامج ايران النووي مقابل تخفيف العقوبات على طهران",
                "subject_role": "Neutral",
                "object_role": "Unknown"
            },
            {
                "subject": "مجلس الأمن الدولي",
                "action": "وافق",
                "object": "قرار",
                "context": "جرى التفاوض عليه في اطار الاتفاق الذي أبرم في فيينا الاسبوع الماضي بين ايران والقوى الست الدولية",
                "subject_role": "Neutral",
                "object_role": "Unknown"
            },
            {
                "subject": "محمد علي جعفري",
                "action": "قال",
                "object": null,
                "context": "ان قرار مجلس الامن الدولي الذي جرى تمريره اليوم، ويقر الاتفاق النووي الايراني غير مقبول",
                "subject_role": "Antagonist",
                "object_role": "Unknown"
            },
            {
                "subject": "بعض أجزاء المسودة",
                "action": "تجاوزت",
                "object": "الخطوط الحمراء لإيران",
                "context": "خاصة ما يتعلق بقدرات ايران العسكرية",
                "subject_role": "Unknown",
                "object_role": "Unknown"
            }
        ]
    },
    {
        "text": "قال مسؤولون أفغان ان 14 جنديا أفغانيا قتلوا في حادث اطلاق \"نيران صديقة\" اليوم (الاثنين)، عندما نفذت قوات حلف شمال الاطلسي ضربة جوية على معسكر للجيش في شرق أفغانستان بطريق الخطأ.\n\n وأكد مسؤول عسكري أميركي في كابل الضربةن وقال ان قوات التحالف الدولية تحقق في الحادث.\n\n وقال محمد رحيم امين حاكم منطقة بركي براك حيث حصلت الغارة، ان \"مروحيتين اميركيتين هاجمتا في الساعة 6:00 صباح اليوم (1:30 ت غ) حاجزا للجيش الافغاني\" مضيفا ان \"النيران اندلعت في الحاجز ودمر بالكامل، وقتل 14 جنديا افغانيا\". كما اكد المتحدث باسم حكومة الولاية دين محمد درويش هذه الحصيلة.\n\n وما زالت طائرات حربية أميركية وطائرات بلا طيار تنفذ ضربات في أفغانستان مستهدفة حركة طالبان ومتطرفين آخرين حتى بعد انسحاب معظم القوات الاجنبية بنهاية العام الماضي.\n\n ونفذت الضربة الجوية صباح اليوم في منطقة بركي برك في اقليم لوغار جنوب العاصمة كابل، حيث كثيرا ما يشن مقاتلو طالبان هجمات على القوات الافغانية.\n\n من جانبه، قال الجنرال عبد الرازق القائد بالجيش الافغاني في لوغار \"يبدو أن الهجوم نفذ بطريق الخطأ على قوات عسكرية وبدأ تحقيق لمعرفة سببه\".\n\n ويذكر هذا الحادث بحادث مماثل وقع في مارس (اذار) 2014 في ولاية لوغار نفسها.\n\n وقد قتل آنذاك خمسة جنود أفغان واصيب ثمانية آخرون بصاروخ اطلقته قوة ايساف التابعة للحلف الاطلسي التي انهت في ديسمبر (كانون الاول) الماضي مهمتها القتالية في افغانستان.\n\n وبعد انسحاب القوات الاطلسية من افغانستان بقي هناك في هذا البلد 12500 جندي اجنبي معظمهم من الاميركيين مكلفون مهمة تدريب القوات الافغانية وتقديم المشورة لها.\n\n وبات الجيش الافغاني وحده في الخطوط الامامية في مواجهة متطرفي طالبان الذين يشنون هجومهم السنوي الواسع النطاق في الربيع والصيف.",
        "entities": {
            "ORG": [
                "حلف شمال الاطلسي",
                "طالبان",
                "ايساف",
                "للح",
                "لف الاطلسي"
            ],
            "LOC": [
                "أفغانستان",
                "كاب",
                "بركي براك",
                "بركي برك",
                "لوغار",
                "كابل",
                "افغانستان"
            ],
            "PERS": [
                "محمد رحيم",
                "دين محمد درويش",
                "عبد الرازق"
            ]
        },
        "labeled_entities": [
            {
                "entity": "أفغانستان",
                "label": "Protagonist"
            },
            {
                "entity": "حلف شمال الاطلسي",
                "label": "Antagonist"
            },
            {
                "entity": "طالبان",
                "label": "Antagonist"
            },
            {
                "entity": "ايساف",
                "label": "Antagonist"
            },
            {
                "entity": "للح",
                "label": "Neutral"
            },
            {
                "entity": "لف الاطلسي",
                "label": "Neutral"
            },
            {
                "entity": "أفغانستان",
                "label": "Neutral"
            },
            {
                "entity": "كاب",
                "label": "Neutral"
            },
            {
                "entity": "بركي براك",
                "label": "Neutral"
            },
            {
                "entity": "بركي برك",
                "label": "Neutral"
            },
            {
                "entity": "لوغار",
                "label": "Neutral"
            },
            {
                "entity": "كابل",
                "label": "Neutral"
            },
            {
                "entity": "افغانستان",
                "label": "Neutral"
            },
            {
                "entity": "محمد رحيم",
                "label": "Neutral"
            },
            {
                "entity": "دين محمد درويش",
                "label": "Neutral"
            },
            {
                "entity": "عبد الرازق",
                "label": "Neutral"
            }
        ],
        "events": [
            {
                "subject": "مسؤولون أفغان",
                "action": "قالوا",
                "object": null,
                "context": "مقتل 14 جنديا أفغانيا في حادث اطلاق 'نيران صديقة'",
                "subject_role": "Unknown",
                "object_role": "Unknown"
            },
            {
                "subject": "قوات حلف شمال الاطلسي",
                "action": "نفذت",
                "object": "ضربة جوية",
                "context": "على معسكر للجيش في شرق أفغانستان بطريق الخطأ",
                "subject_role": "Antagonist",
                "object_role": "Unknown"
            },
            {
                "subject": "مسؤول عسكري أميركي",
                "action": "أكد",
                "object": "الضربة",
                "context": "في كابل",
                "subject_role": "Unknown",
                "object_role": "Unknown"
            },
            {
                "subject": "قوات التحالف الدولية",
                "action": "تحقق",
                "object": "الحادث",
                "context": null,
                "subject_role": "Unknown",
                "object_role": "Unknown"
            },
            {
                "subject": "محمد رحيم امين حاكم منطقة بركي براك",
                "action": "قال",
                "object": null,
                "context": " 'مروحيتين اميركيتين هاجمتا في الساعة 6:00 صباح اليوم (1:30 ت غ) حاجزا للجيش الافغاني' مضيفا ان 'النيران اندلعت في الحاجز ودمر بالكامل، وقتل 14 جنديا افغانيا'",
                "subject_role": "Unknown",
                "object_role": "Unknown"
            },
            {
                "subject": "دين محمد درويش",
                "action": "أكد",
                "object": "الحصيلة",
                "context": "المتحدث باسم حكومة الولاية",
                "subject_role": "Neutral",
                "object_role": "Unknown"
            },
            {
                "subject": "طائرات حربية أميركية وطائرات بلا طيار",
                "action": "تنفذ",
                "object": "ضربات",
                "context": "في أفغانستان مستهدفة حركة طالبان ومتطرفين آخرين",
                "subject_role": "Unknown",
                "object_role": "Unknown"
            },
            {
                "subject": "مقاتلو طالبان",
                "action": "يشنون",
                "object": "هجمات",
                "context": "على القوات الافغانية في منطقة بركي برك في اقليم لوغار جنوب العاصمة كابل",
                "subject_role": "Antagonist",
                "object_role": "Unknown"
            },
            {
                "subject": "عبد الرازق القائد بالجيش الافغاني",
                "action": "قال",
                "object": null,
                "context": "في لوغار 'يبدو أن الهجوم نفذ بطريق الخطأ على قوات عسكرية وبدأ تحقيق لمعرفة سببه'",
                "subject_role": "Unknown",
                "object_role": "Unknown"
            },
            {
                "subject": "قوة ايساف التابعة للحلف الاطلسي",
                "action": "أطلقت",
                "object": "صاروخ",
                "context": "في ولاية لوغار",
                "subject_role": "Unknown",
                "object_role": "Unknown"
            },
            {
                "subject": "الجيش الافغاني",
                "action": "يواجه",
                "object": "متطرفي طالبان",
                "context": "في الخطوط الامامية",
                "subject_role": "Unknown",
                "object_role": "Antagonist"
            },
            {
                "subject": "طالبان",
                "action": "يشنون",
                "object": "هجومهم",
                "context": "السنوي الواسع النطاق في الربيع والصيف",
                "subject_role": "Antagonist",
                "object_role": "Unknown"
            }
        ]
    },
    {
        "text": "أعلنت وزارة الخارجية الايطالية، اليوم (الاثنين)، ان اربعة ايطاليين يعملون في مجال البناء خطفوا في ليبيا.\n\n وقالت الوزارة في بيان ان الايطاليين الاربعة كانوا عند خطفهم في محيط مجمع الشركة النفطية الايطالية ايني في منطقة مليتة غرب طرابلس.\n\n وقال وزير الخارجية الايطالي باولو جينتيلوني \"انها منطقة شهدت سوابق\" من قبل. واضاف لشبكات التلفزيون الايطالية \"ما زال من الصعب بعد ساعات فقط (على خطفهم) معرفة المسؤولين وفهم طبيعة\" عملية الخطف.\n\n وشكلت خلية أزمة على الفور لمتابعة القضية وهي \"على اتصال مستمر مع عائلات (الايطاليين المخطوفين) وشركة بوناتي\" التي يعملون لحسابها.\n\n وذكرت الوزارة بان السفارة الايطالية في ليبيا مغلقة منذ 15 فبراير (شباط)، وبأن الايطاليين دعوا لمغادرة البلاد التي تواجه \"صعوبات جمة\".",
        "entities": {
            "LOC": [
                "ليبيا",
                "مليتة",
                "طرابلس"
            ],
            "ORG": [
                "اين",
                "بوناتي"
            ],
            "PERS": [
                "باولو جينتيلوني"
            ]
        },
        "labeled_entities": [
            {
                "entity": "ليبيا",
                "label": "Neutral"
            },
            {
                "entity": "مليتة",
                "label": "Neutral"
            },
            {
                "entity": "طرابلس",
                "label": "Neutral"
            },
            {
                "entity": "اين",
                "label": "Neutral"
            },
            {
                "entity": "بوناتي",
                "label": "Neutral"
            },
            {
                "entity": "باولو جينتيلوني",
                "label": "Neutral"
            }
        ],
        "events": [
            {
                "subject": "وزارة الخارجية الايطالية",
                "action": "أعلنت",
                "object": "خطف",
                "context": "أربعة ايطاليين يعملون في مجال البناء في ليبيا",
                "subject_role": "Unknown",
                "object_role": "Unknown"
            },
            {
                "subject": "الوزارة",
                "action": "قالت",
                "object": null,
                "context": "الايطاليين الاربعة كانوا عند خطفهم في محيط مجمع الشركة النفطية الايطالية ايني في منطقة مليتة غرب طرابلس",
                "subject_role": "Unknown",
                "object_role": "Unknown"
            },
            {
                "subject": "وزير الخارجية الايطالي باولو جينتيلوني",
                "action": "قال",
                "object": null,
                "context": "انها منطقة شهدت سوابق من قبل",
                "subject_role": "Unknown",
                "object_role": "Unknown"
            },
            {
                "subject": "وزير الخارجية الايطالي باولو جينتيلوني",
                "action": "اضاف",
                "object": null,
                "context": "ما زال من الصعب بعد ساعات فقط (على خطفهم) معرفة المسؤولين وفهم طبيعة عملية الخطف",
                "subject_role": "Unknown",
                "object_role": "Unknown"
            },
            {
                "subject": "خلية أزمة",
                "action": "شكلت",
                "object": null,
                "context": "لمتابعة القضية وهي على اتصال مستمر مع عائلات (الايطاليين المخطوفين) وشركة بوناتي التي يعملون لحسابها",
                "subject_role": "Unknown",
                "object_role": "Unknown"
            },
            {
                "subject": "الوزارة",
                "action": "ذكرت",
                "object": null,
                "context": "بان السفارة الايطالية في ليبيا مغلقة منذ 15 فبراير (شباط)، وبأن الايطاليين دعوا لمغادرة البلاد التي تواجه صعوبات جمة",
                "subject_role": "Unknown",
                "object_role": "Unknown"
            }
        ]
    },
    {
        "text": "ارتكبت الميليشيات الحوثية مجزرة في مدينة عدن، جنوب اليمن، بعدما أمطرت ضاحية دار سعد شمال المدينة بصواريخ الكاتيوشا وقنابل الهاون مما أدى إلى مقتل 43 مدنيا على الأقل وإصابة 173.\n\n وجاء هذا القصف بينما استمرت الاشتباكات في دار سعد وصبر وفي منطقة المعاشيق بمديرية كريتر في شمال المدينة، فيما واصل عناصر المقاومة الشعبية زحفهم نحو القصر الرئاسي في حي التواهي لتحريره من سيطرة المتمردين، وذلك بعد أيام من إعلان حكومة الرئيس اليمني عبد ربه منصور هادي تحرير المدينة باستثناء جيوب لميليشيات الحوثيين وحليفهم الرئيس السابق علي عبد الله صالح.\n\n ودخلت «المقاومة الشعبية» ليلا إلى حي التواهي، وقال مصدر عسكري إن تلك القوات «تتقدم باتجاه قصر رئاسة الجمهورية ومقر قيادة الفرقة الرابعة للجيش»، كما مشطت مقر الإذاعة والتلفزيون.\n\n وذكر مصدر عسكري آخر أن المقاتلين على الأرض استفادوا من دعم مقاتلات التحالف العربي الذي شن نحو 15 غارة على مواقع المتمردين الحوثيين في التواهي وكذلك في الضاحيتين الشمالية والشرقية لعدن.\n\n في غضون ذلك، سيطرت قوات المقاومة الشعبية في محافظتي الضالع وعدن على «مثلث العند» وهو مفترق طرق يربط بين مدن ردفان والضالع وتعز ولحج بعدن، وذلك في سياق التحضيرات الجارية لتحرير «قاعدة العند» العسكرية الاستراتيجية التي لا تبعد سوى بضعة كيلومترات عن المثلث.\n\n في المقابل، حمل الحوثيون الأمم المتحدة «ضمنيا» مسؤولية هزائمهم على الأرض، واتهموها بالتورط بعد سكوتها عن «خرق الهدنة». ولوح محمد عبد السلام، الناطق باسم المتمردين، بوقف التعامل مع المنظمة الدولية مستقبلا.\n\n من جهة أخرى، يبدأ وزير الخارجية اليمني رياض ياسين غدًا جولة أوروبية تشمل بريطانيا وبلجيكا وفرنسا، لتفعيل الشراكة اليمنية مع تلك الدول، ومناقشتهم حول مسألة الإغاثة الإنسانية والطبية، وإعادة إعمار اليمن، ابتداء من عدن.\n\n وكشف ياسين لـ«الشرق الأوسط» عن توجه حكومته لمحاسبة عدد من المسؤولين اليمنيين بعد محاولتهم «التباحث أو فتح علاقات جديدة أو التواطؤ مع المتمردين على الشرعية من الميليشيات الحوثية وأتباع المخلوع صالح».\n\n ...المزيد",
        "entities": {
            "LOC": [
                "عدن",
                "اليمن",
                "دار سعد",
                "وصبر",
                "المعاشيق",
                "كريتر",
                "التواهي",
                "التوا",
                "هي",
                "لعد",
                "ن",
                "الضالع",
                "وعد",
                "العند",
                "ردفان",
                "والض",
                "الع",
                "وتع",
                "ز",
                "ولح",
                "ج",
                "بعد",
                "بريطانيا",
                "وب",
                "لجيكا",
                "وفرنسا"
            ],
            "MISC": [
                "الكات",
                "ي",
                "وش"
            ],
            "PERS": [
                "عبد ربه منصور هادي",
                "علي عبد الله صالح",
                "محمد عبد السلام",
                "رياض ياسين",
                "ياسين",
                "المخلوع",
                "صالح"
            ],
            "ORG": [
                "الأمم المتحدة",
                "الشرق الأوسط"
            ]
        },
        "labeled_entities": [
            {
                "entity": "عدن",
                "label": "Neutral"
            },
            {
                "entity": "اليمن",
                "label": "Neutral"
            },
            {
                "entity": "دار سعد",
                "label": "Neutral"
            },
            {
                "entity": "وصبر",
                "label": "Neutral"
            },
            {
                "entity": "المعاشيق",
                "label": "Neutral"
            },
            {
                "entity": "كريتر",
                "label": "Neutral"
            },
            {
                "entity": "التواهي",
                "label": "Neutral"
            },
            {
                "entity": "التوا",
                "label": "Neutral"
            },
            {
                "entity": "هي",
                "label": "Neutral"
            },
            {
                "entity": "لعد",
                "label": "Neutral"
            },
            {
                "entity": "ن",
                "label": "Neutral"
            },
            {
                "entity": "الضالع",
                "label": "Neutral"
            },
            {
                "entity": "وعد",
                "label": "Neutral"
            },
            {
                "entity": "العند",
                "label": "Neutral"
            },
            {
                "entity": "ردفان",
                "label": "Neutral"
            },
            {
                "entity": "والض",
                "label": "Neutral"
            },
            {
                "entity": "الع",
                "label": "Neutral"
            },
            {
                "entity": "وتع",
                "label": "Neutral"
            },
            {
                "entity": "ز",
                "label": "Neutral"
            },
            {
                "entity": "ولح",
                "label": "Neutral"
            },
            {
                "entity": "ج",
                "label": "Neutral"
            },
            {
                "entity": "بعد",
                "label": "Neutral"
            },
            {
                "entity": "بريطانيا",
                "label": "Neutral"
            },
            {
                "entity": "وب",
                "label": "Neutral"
            },
            {
                "entity": "لجيكا",
                "label": "Neutral"
            },
            {
                "entity": "وفرنسا",
                "label": "Neutral"
            },
            {
                "entity": "الكات",
                "label": "Antagonist"
            },
            {
                "entity": "ي",
                "label": "Antagonist"
            },
            {
                "entity": "وش",
                "label": "Antagonist"
            },
            {
                "entity": "عبد ربه منصور هادي",
                "label": "Protagonist"
            },
            {
                "entity": "علي عبد الله صالح",
                "label": "Antagonist"
            },
            {
                "entity": "محمد عبد السلام",
                "label": "Antagonist"
            },
            {
                "entity": "رياض ياسين",
                "label": "Protagonist"
            },
            {
                "entity": "ياسين",
                "label": "Protagonist"
            },
            {
                "entity": "المخلوع",
                "label": "Antagonist"
            },
            {
                "entity": "صالح",
                "label": "Antagonist"
            },
            {
                "entity": "الأمم المتحدة",
                "label": "Neutral"
            },
            {
                "entity": "الشرق الأوسط",
                "label": "Neutral"
            }
        ],
        "events": [
            {
                "subject": "الميليشيات الحوثية",
                "action": "ارتكبت",
                "object": "مجزرة",
                "context": "في مدينة عدن، جنوب اليمن، بعدما أمطرت ضاحية دار سعد شمال المدينة بصواريخ الكاتيوشا وقنابل الهاون مما أدى إلى مقتل 43 مدنيا على الأقل وإصابة 173",
                "subject_role": "Unknown",
                "object_role": "Unknown"
            },
            {
                "subject": "الاشتباكات",
                "action": "استمرت",
                "object": null,
                "context": "في دار سعد وصبر وفي منطقة المعاشيق بمديرية كريتر في شمال المدينة",
                "subject_role": "Antagonist",
                "object_role": "Unknown"
            },
            {
                "subject": "عناصر المقاومة الشعبية",
                "action": "واصلوا",
                "object": "زحفهم",
                "context": "نحو القصر الرئاسي في حي التواهي لتحريره من سيطرة المتمردين",
                "subject_role": "Unknown",
                "object_role": "Unknown"
            },
            {
                "subject": "حكومة الرئيس اليمني عبد ربه منصور هادي",
                "action": "أعلنت",
                "object": "تحرير المدينة",
                "context": "باستثناء جيوب لميليشيات الحوثيين وحليفهم الرئيس السابق علي عبد الله صالح",
                "subject_role": "Protagonist",
                "object_role": "Unknown"
            },
            {
                "subject": "المقاومة الشعبية",
                "action": "دخلت",
                "object": "حي التواهي",
                "context": "ليلا",
                "subject_role": "Unknown",
                "object_role": "Neutral"
            },
            {
                "subject": "قوات",
                "action": "تتقدم",
                "object": null,
                "context": "باتجاه قصر رئاسة الجمهورية ومقر قيادة الفرقة الرابعة للجيش",
                "subject_role": "Unknown",
                "object_role": "Unknown"
            },
            {
                "subject": "قوات",
                "action": "مشطت",
                "object": "مقر الإذاعة والتلفزيون",
                "context": null,
                "subject_role": "Unknown",
                "object_role": "Unknown"
            },
            {
                "subject": "المقاتلين",
                "action": "استفادوا",
                "object": "دعم",
                "context": "من دعم مقاتلات التحالف العربي الذي شن نحو 15 غارة على مواقع المتمردين الحوثيين في التواهي وكذلك في الضاحيتين الشمالية والشرقية لعدن",
                "subject_role": "Unknown",
                "object_role": "Unknown"
            },
            {
                "subject": "قوات المقاومة الشعبية",
                "action": "سيطرت",
                "object": "مثلث العند",
                "context": "في محافظتي الضالع وعدن",
                "subject_role": "Unknown",
                "object_role": "Neutral"
            },
            {
                "subject": "الحوثيون",
                "action": "حملوا",
                "object": "الأمم المتحدة",
                "context": "«ضمنيا» مسؤولية هزائمهم على الأرض، واتهموها بالتورط بعد سكوتها عن «خرق الهدنة»",
                "subject_role": "Neutral",
                "object_role": "Neutral"
            },
            {
                "subject": "محمد عبد السلام",
                "action": "لوح",
                "object": "وقف التعامل",
                "context": "مع المنظمة الدولية مستقبلا",
                "subject_role": "Antagonist",
                "object_role": "Unknown"
            },
            {
                "subject": "وزير الخارجية اليمني رياض ياسين",
                "action": "يبدأ",
                "object": "جولة أوروبية",
                "context": "تشمل بريطانيا وبلجيكا وفرنسا، لتفعيل الشراكة اليمنية مع تلك الدول، ومناقشتهم حول مسألة الإغاثة الإنسانية والطبية، وإعادة إعمار اليمن، ابتداء من عدن",
                "subject_role": "Unknown",
                "object_role": "Unknown"
            },
            {
                "subject": "ياسين",
                "action": "كشف",
                "object": "توجه حكومته",
                "context": "لمحاسبة عدد من المسؤولين اليمنيين بعد محاولتهم «التباحث أو فتح علاقات جديدة أو التواطؤ مع المتمردين على الشرعية من الميليشيات الحوثية وأتباع المخلوع صالح»",
                "subject_role": "Protagonist",
                "object_role": "Unknown"
            }
        ]
    },
    {
        "text": "في تحد جديد للكونغرس الأميركي، رفض الرئيس باراك أوباما مطالب أعضائه بالتمهل في عرض الاتفاق النووي مع إيران على مجلس الأمن الدولي، وقرر المضي قدمًا وطرحه للمناقشة في المجلس. وطلب أوباما من وزير الخارجية، جون كيري، وسفيرة الولايات المتحدة لدى الأمم المتحدة، سامنثا باور، الالتزام بالاتفاق الذي أبرم في فيينا مع بقية الأطراف الدولية، وعرضه على مجلس الأمن اليوم. ودافع كيري عن قرار الرئيس أوباما, قائلا «وقعنا على اتفاق تاريخي (..) حسب الاتفاق، يجب عرضه على مجلس الأمن في أقرب فرصة ممكنة». غير أن كيري أكد في الوقت نفسه أن إيران لا تزال عدوًا للولايات المتحدة. وقال «ما زلنا أعداء.. لسنا حلفاء أو أصدقاء».\n\n في غضون ذلك، أحالت وزارة الخارجية نص الاتفاق إلى الكونغرس الذي أمامه 60 يومًا للتصويت عليه.\n\n وفي طهران، أعلن عضو مجلس الشورى، حسين نقوي حسيني، أن البرلمان يريد الاطلاع فورًا على نص الاتفاق، بينما ينتظر أن يمثل وزير الخارجية، محمد جواد ظريف، ورئيس منظمة الطاقة الذرية، علي أكبر صالحي، غدًا أمام النواب لاستجوابهما بشأن الاتفاق.\n\n ...المزيد",
        "entities": {
            "ORG": [
                "للك",
                "ونغرس",
                "مجلس الأمن الدولي",
                "المتحدة",
                "الأمم المتحدة",
                "مجلس الأمن",
                "الكونغرس",
                "مجلس الشورى",
                "منظمة الطاقة الذرية"
            ],
            "PERS": [
                "باراك أوباما",
                "أوباما",
                "جون كيري",
                "سام",
                "نثا باور",
                "كيري",
                "حسين نقوي حسيني",
                "محمد جواد ظريف",
                "علي أكبر صالحي"
            ],
            "LOC": [
                "إيران",
                "الولايات",
                "فيينا",
                "للولايات المتحدة",
                "طهران"
            ]
        },
        "labeled_entities": [
            {
                "entity": "الكونغرس",
                "label": "Antagonist"
            },
            {
                "entity": "مجلس الأمن الدولي",
                "label": "Neutral"
            },
            {
                "entity": "الأمم المتحدة",
                "label": "Neutral"
            },
            {
                "entity": "مجلس الأمن",
                "label": "Neutral"
            },
            {
                "entity": "باراك أوباما",
                "label": "Protagonist"
            },
            {
                "entity": "أوباما",
                "label": "Protagonist"
            },
            {
                "entity": "جون كيري",
                "label": "Protagonist"
            },
            {
                "entity": "سامنثا باور",
                "label": "Protagonist"
            },
            {
                "entity": "كيري",
                "label": "Protagonist"
            },
            {
                "entity": "حسين نقوي حسيني",
                "label": "Neutral"
            },
            {
                "entity": "محمد جواد ظريف",
                "label": "Neutral"
            },
            {
                "entity": "علي أكبر صالحي",
                "label": "Neutral"
            },
            {
                "entity": "إيران",
                "label": "Neutral"
            }
        ],
        "events": [
            {
                "subject": "باراك أوباما",
                "action": "رفض",
                "object": "مطالب",
                "context": "بالتمهل في عرض الاتفاق النووي مع إيران على مجلس الأمن الدولي",
                "subject_role": "Protagonist",
                "object_role": "Unknown"
            },
            {
                "subject": "باراك أوباما",
                "action": "قرر",
                "object": "المضي",
                "context": "وطرح الاتفاق النووي مع إيران للمناقشة في مجلس الأمن الدولي",
                "subject_role": "Protagonist",
                "object_role": "Unknown"
            },
            {
                "subject": "أوباما",
                "action": "طلب",
                "object": "الالتزام",
                "context": "من جون كيري وسام نثا باور بالاتفاق الذي أبرم في فيينا وعرضه على مجلس الأمن",
                "subject_role": "Protagonist",
                "object_role": "Unknown"
            },
            {
                "subject": "جون كيري",
                "action": "دافع",
                "object": "قرار",
                "context": "قرار الرئيس أوباما",
                "subject_role": "Protagonist",
                "object_role": "Unknown"
            },
            {
                "subject": "جون كيري",
                "action": "أكد",
                "object": "إيران",
                "context": "لا تزال عدوًا للولايات المتحدة",
                "subject_role": "Protagonist",
                "object_role": "Neutral"
            },
            {
                "subject": "وزارة الخارجية",
                "action": "أحالت",
                "object": "نص الاتفاق",
                "context": "إلى الكونغرس",
                "subject_role": "Unknown",
                "object_role": "Unknown"
            },
            {
                "subject": "حسين نقوي حسيني",
                "action": "أعلن",
                "object": "البرلمان",
                "context": "يريد الاطلاع فورًا على نص الاتفاق",
                "subject_role": "Neutral",
                "object_role": "Unknown"
            },
            {
                "subject": "محمد جواد ظريف",
                "action": "يمثل",
                "object": null,
                "context": "أمام النواب لاستجوابهما بشأن الاتفاق",
                "subject_role": "Neutral",
                "object_role": "Unknown"
            },
            {
                "subject": "علي أكبر صالحي",
                "action": "يمثل",
                "object": null,
                "context": "أمام النواب لاستجوابهما بشأن الاتفاق",
                "subject_role": "Neutral",
                "object_role": "Unknown"
            }
        ]
    },
    {
        "text": "أفاق سكان حي الشيخ رضوان وشارع النفق وسط مدينة غزة، على انفجارات ضخمة استهدفت سيارات قياديين في كتائب القسام التابعة لحركة حماس وسرايا القدس التابعة لـ{الجهاد الإسلامي}، وأسفرت عن تدمير خمس سيارات دون وقوع إصابات بشرية.\n\n وتعد التفجيرات التحدي الأقوى لحركة حماس الحاكمة في قطاع غزة، ورسالة هي الأوضح، إذ استهدفت مباشرة، الذراع المسلحة للحركة للمرة الأولى، بعدما كانت التهديدات والانفجارات السابقة، تستهدف مواقع فارغة قريبة من مبان حكومية.\n\n جاء هذا بعد 3 أسابيع من تهديدات تنظيم داعش لحماس. وقد عثر فعلا على شعارات في أماكن التفجيرات، تشير إلى التنظيم، من دون أن يتأكد بشكل مستقل، من يقف خلف الهجمات الخمس.\n\n من جانبها، لم تتهم وزارة الداخلية في غزة أي طرف، واكتفى الناطق باسمها إياد البزم بالقول، إن «عناصر تخريبية أقدمت على تفجير عدد من السيارات التي تتبع فصائل المقاومة في منطقة الشيخ رضوان، خلفت أضرارا مادية».\n\n وكان متحدثون من «داعش»، هددوا حماس، في بداية الشهر الحالي، بـ«شلالات من الدماء».\n\n ...المزيد",
        "entities": {
            "LOC": [
                "الشيخ رضوان",
                "غزة"
            ],
            "ORG": [
                "القسام",
                "حماس",
                "ايا القدس",
                "الجهاد الإسلامي",
                "داعش",
                "لحم",
                "اس"
            ],
            "PERS": [
                "إي",
                "اد البزم"
            ]
        },
        "labeled_entities": [
            {
                "entity": "الشيخ رضوان",
                "label": "Neutral"
            },
            {
                "entity": "غزة",
                "label": "Neutral"
            },
            {
                "entity": "القسام",
                "label": "Neutral"
            },
            {
                "entity": "حماس",
                "label": "Protagonist"
            },
            {
                "entity": "ايا القدس",
                "label": "Neutral"
            },
            {
                "entity": "الجهاد الإسلامي",
                "label": "Neutral"
            },
            {
                "entity": "داعش",
                "label": "Antagonist"
            },
            {
                "entity": "لحم",
                "label": "Neutral"
            },
            {
                "entity": "اس",
                "label": "Neutral"
            },
            {
                "entity": "إي",
                "label": "Neutral"
            },
            {
                "entity": "اد البزم",
                "label": "Neutral"
            }
        ],
        "events": [
            {
                "subject": "سكان",
                "action": "أفاق",
                "object": "على انفجارات",
                "context": "في حي الشيخ رضوان وشارع النفق وسط مدينة غزة",
                "subject_role": "Unknown",
                "object_role": "Unknown"
            },
            {
                "subject": "انفجارات",
                "action": "استهدفت",
                "object": "سيارات",
                "context": "قياديين في كتائب القسام التابعة لحركة حماس وسرايا القدس التابعة للجهاد الإسلامي",
                "subject_role": "Unknown",
                "object_role": "Unknown"
            },
            {
                "subject": "التفجيرات",
                "action": "أسفرت",
                "object": "تدمير",
                "context": "خمس سيارات دون وقوع إصابات بشرية",
                "subject_role": "Unknown",
                "object_role": "Unknown"
            },
            {
                "subject": "التفجيرات",
                "action": "تعد",
                "object": "التحدي",
                "context": "الأقوى لحركة حماس الحاكمة في قطاع غزة",
                "subject_role": "Unknown",
                "object_role": "Unknown"
            },
            {
                "subject": "التفجيرات",
                "action": "استهدفت",
                "object": "الذراع المسلحة",
                "context": "للحركة للمرة الأولى",
                "subject_role": "Unknown",
                "object_role": "Unknown"
            },
            {
                "subject": "تهديدات وانفجارات",
                "action": "تستهدف",
                "object": "مواقع",
                "context": "فارغة قريبة من مبان حكومية",
                "subject_role": "Unknown",
                "object_role": "Unknown"
            },
            {
                "subject": "هذا",
                "action": "جاء",
                "object": null,
                "context": "بعد 3 أسابيع من تهديدات تنظيم داعش لحماس",
                "subject_role": "Unknown",
                "object_role": "Unknown"
            },
            {
                "subject": "شعارات",
                "action": "عثر",
                "object": "على شعارات",
                "context": "في أماكن التفجيرات تشير إلى التنظيم",
                "subject_role": "Unknown",
                "object_role": "Unknown"
            },
            {
                "subject": "وزارة الداخلية",
                "action": "تتهم",
                "object": "طرف",
                "context": "في غزة",
                "subject_role": "Unknown",
                "object_role": "Unknown"
            },
            {
                "subject": "إياد البزم",
                "action": "قال",
                "object": "عناصر",
                "context": "إن عناصر تخريبية أقدمت على تفجير عدد من السيارات التي تتبع فصائل المقاومة في منطقة الشيخ رضوان",
                "subject_role": "Neutral",
                "object_role": "Unknown"
            },
            {
                "subject": "عناصر",
                "action": "خلفت",
                "object": "أضرارا",
                "context": "مادية",
                "subject_role": "Unknown",
                "object_role": "Unknown"
            },
            {
                "subject": "متحدثون",
                "action": "هددوا",
                "object": "حماس",
                "context": "من داعش في بداية الشهر الحالي بـ «شلالات من الدماء»",
                "subject_role": "Unknown",
                "object_role": "Protagonist"
            }
        ]
    },
    {
        "text": "تحول «فقهاء» وقادة تنظيم داعش في ليبيا إلى نوع جديد من الخطب لا صلة لها بتطبيق الشريعة الإسلامية، كما كان في السابق، ولكن بإطلاق «فتاوى نفطية» تعد المقاتلين بالثراء وتشيع إمكانية تصدير النفط الليبي عبر وسطاء في البحر المتوسط.\n\n وفي مدينة سرت يروج التنظيم لشعارات مثل «بترول ليبيا للمسلمين» وأخرى للثراء الذي ينتظر رعايا «دويلته» في المستقبل، نظرا للمخزون النفطي الضخم الذي يقع في المناطق المحيطة بالمدينة، التي تعرف باسم «الهلال النفطي»، وتحوي أكثر من 60 في المائة من النفط الليبي.\n\n إلا أن المحلل المتخصّص في شؤون شمال أفريقيا في مركز «الأهرام» للدراسات السياسية والاستراتيجية كامل عبد الله يشكك بهذا الأمر، ويرى أن قدرة «داعش» على تصدير النفط «وهمٌ كبير». ويوضح قائلا لـ«الشرق الأوسط» إنه «من السهل على (داعش) تصدير النفط من المناطق التي يسيطر عليها في العراق وسوريا، لأن الأمر يجري هناك بطرق معقدة والتفافية، لكن في حالة ليبيا يمكن مراقبة السواحل.. كل شيء واضح ومن السهل اكتشافه». وعبر عن اعتقاده بأن خطاب «داعش» موجَّه في الأغلب إلى المقاتلين الأجانب لإغرائهم بالقدوم إلى ليبيا.\n\n غير أن محللين آخرين يرون أن «داعش» يلعب على الوتر الاقتصادي في أوساط الشباب العاطل عن العمل في ليبيا والمحبط من انسداد العملية السياسية.\n\n ...المزيد",
        "entities": {
            "ORG": [
                "داعش",
                "الأهرام"
            ],
            "LOC": [
                "ليبيا",
                "البحر المتوسط",
                "سرت",
                "أفريقيا",
                "الشرق الأوسط",
                "العراق",
                "وسوريا"
            ],
            "PERS": [
                "كامل عبد الله"
            ]
        },
        "labeled_entities": [
            {
                "entity": "داعش",
                "label": "Antagonist"
            },
            {
                "entity": "الأهرام",
                "label": "Neutral"
            },
            {
                "entity": "ليبيا",
                "label": "Neutral"
            },
            {
                "entity": "البحر المتوسط",
                "label": "Neutral"
            },
            {
                "entity": "سرت",
                "label": "Neutral"
            },
            {
                "entity": "أفريقيا",
                "label": "Neutral"
            },
            {
                "entity": "الشرق الأوسط",
                "label": "Neutral"
            },
            {
                "entity": "العراق",
                "label": "Neutral"
            },
            {
                "entity": "وسوريا",
                "label": "Neutral"
            },
            {
                "entity": "كامل عبد الله",
                "label": "Neutral"
            }
        ],
        "events": [
            {
                "subject": "فقهاء وقادة تنظيم داعش",
                "action": "تحول",
                "object": "نوع جديد من الخطب",
                "context": "في ليبيا، لا صلة لها بتطبيق الشريعة الإسلامية، ولكن بإطلاق «فتاوى نفطية» تعد المقاتلين بالثراء وتشيع إمكانية تصدير النفط الليبي عبر وسطاء في البحر المتوسط",
                "subject_role": "Unknown",
                "object_role": "Unknown"
            },
            {
                "subject": "التنظيم",
                "action": "يروج",
                "object": "شعارات",
                "context": "في مدينة سرت، مثل «بترول ليبيا للمسلمين» وأخرى للثراء الذي ينتظر رعايا «دويلته» في المستقبل، نظرا للمخزون النفطي الضخم الذي يقع في المناطق المحيطة بالمدينة، التي تعرف باسم «الهلال النفطي»، وتحوي أكثر من 60 في المائة من النفط الليبي",
                "subject_role": "Unknown",
                "object_role": "Unknown"
            },
            {
                "subject": "كامل عبد الله",
                "action": "يشكك",
                "object": "قدرة «داعش» على تصدير النفط",
                "context": "ويرى أنها «وهمٌ كبير»",
                "subject_role": "Neutral",
                "object_role": "Unknown"
            },
            {
                "subject": "داعش",
                "action": "يصدر",
                "object": "النفط",
                "context": "من المناطق التي يسيطر عليها في العراق وسوريا",
                "subject_role": "Antagonist",
                "object_role": "Unknown"
            },
            {
                "subject": "داعش",
                "action": "موجَّه",
                "object": "خطاب",
                "context": "في الأغلب إلى المقاتلين الأجانب لإغرائهم بالقدوم إلى ليبيا",
                "subject_role": "Antagonist",
                "object_role": "Unknown"
            },
            {
                "subject": "داعش",
                "action": "يلعب",
                "object": "الوتر الاقتصادي",
                "context": "في أوساط الشباب العاطل عن العمل في ليبيا والمحبط من انسداد العملية السياسية",
                "subject_role": "Antagonist",
                "object_role": "Unknown"
            }
        ]
    },
    {
        "text": "وسط تفاقم أزمات الكهرباء والماء في السودان، لوحت حكومة الرئيس السوداني عمر حسن البشير بغصن الزيتون أمام خصومها ودعت بنبرة تصالحية واضحة إلى وقف الاقتتال وعقد حوار مع المعارضة.\n\n ودعا نائب الرئيس السوداني في حزب «المؤتمر الوطني» إبراهيم محمود في حفل بمناسبة عيد الفطر أقامه الحزب الحاكم «المؤتمر الوطني» بحضور البشير إلى الحفاظ على عقد الأمن من الانفراط والدخول في الحوار الوطني، وتحقيق الأمن والسلام والاستقرار في البلاد ووضع حد لـ«الإرهابيين».\n\n وأضاف محمود في كلمة «حققنا أمنياتنا الواضحة من خلال برنامج رئيس المؤتمر الوطني، ومن خطابه وهو يدعو أهل السودان ويتمنى لهم الوحدة والوفاق، عبر برنامج للحوار الوطني لا يستثني أحدًا، والذي يسير فيه بخطى واثقة».\n\n وتجيء هذه الدعوة مع تصاعد الغليان الشعبي جراء نقص الكهرباء والمياه وارتفاع أسعار المعيشية إلى أرقام «خرافية»، وفشل وزارة المالية السودانية في استقطاب النقد الأجنبي، لتمويل واردات الوقود، بالإضافة إلى الأوضاع الأمنية المتدهورة.\n\n ووعد محمود بتحقيق «أماني أهل السودان في السلام والأمن والاستقرار»، لكنه حذر من انتقال الإرهاب في بعض بلدان الجوار والإقليم إلى السودان بقوله «سنضع حدًا للذين يريدون أن يكون السودان مثل الدول الأخرى، ينفرط فيه عقد الأمن».\n\n ...المزيد",
        "entities": {
            "LOC": [
                "السودان"
            ],
            "PERS": [
                "عمر حسن البشير",
                "إبراهيم محمود",
                "البشير",
                "محمود"
            ],
            "ORG": [
                "المؤتمر الوطني"
            ]
        },
        "labeled_entities": [
            {
                "entity": "عمر حسن البشير",
                "label": "Protagonist"
            },
            {
                "entity": "إبراهيم محمود",
                "label": "Protagonist"
            },
            {
                "entity": "البشير",
                "label": "Protagonist"
            },
            {
                "entity": "محمود",
                "label": "Protagonist"
            },
            {
                "entity": "السودان",
                "label": "Neutral"
            },
            {
                "entity": "المؤتمر الوطني",
                "label": "Neutral"
            }
        ],
        "events": [
            {
                "subject": "حكومة الرئيس السوداني عمر حسن البشير",
                "action": "لوحت",
                "object": "غصن الزيتون",
                "context": "أمام خصومها وسط تفاقم أزمات الكهرباء والماء في السودان",
                "subject_role": "Unknown",
                "object_role": "Unknown"
            },
            {
                "subject": "حكومة الرئيس السوداني عمر حسن البشير",
                "action": "دعت",
                "object": "إلى وقف الاقتتال وعقد حوار مع المعارضة",
                "context": "بنبرة تصالحية واضحة",
                "subject_role": "Unknown",
                "object_role": "Unknown"
            },
            {
                "subject": "نائب الرئيس السوداني إبراهيم محمود",
                "action": "دعا",
                "object": "إلى الحفاظ على عقد الأمن من الانفراط والدخول في الحوار الوطني، وتحقيق الأمن والسلام والاستقرار في البلاد ووضع حد لـ«الإرهابيين»",
                "context": "في حفل بمناسبة عيد الفطر أقامه الحزب الحاكم «المؤتمر الوطني» بحضور البشير",
                "subject_role": "Unknown",
                "object_role": "Unknown"
            },
            {
                "subject": "محمود",
                "action": "أضاف",
                "object": "حققنا أمنياتنا الواضحة من خلال برنامج رئيس المؤتمر الوطني، ومن خطابه وهو يدعو أهل السودان ويتمنى لهم الوحدة والوفاق، عبر برنامج للحوار الوطني لا يستثني أحدًا، والذي يسير فيه بخطى واثقة",
                "context": "في كلمة",
                "subject_role": "Protagonist",
                "object_role": "Unknown"
            },
            {
                "subject": "وزارة المالية السودانية",
                "action": "فشلت",
                "object": "في استقطاب النقد الأجنبي",
                "context": "لتمويل واردات الوقود",
                "subject_role": "Unknown",
                "object_role": "Unknown"
            },
            {
                "subject": "محمود",
                "action": "وعد",
                "object": "بتحقيق «أماني أهل السودان في السلام والأمن والاستقرار»",
                "subject_role": "Protagonist",
                "object_role": "Unknown"
            },
            {
                "subject": "محمود",
                "action": "حذر",
                "object": "من انتقال الإرهاب في بعض بلدان الجوار والإقليم إلى السودان",
                "context": "بقوله «سنضع حدًا للذين يريدون أن يكون السودان مثل الدول الأخرى، ينفرط فيه عقد الأمن»",
                "subject_role": "Protagonist",
                "object_role": "Unknown"
            }
        ]
    },
    {
        "text": "عقد أعضاء في الحكومة اليمنية ومسؤولون أمنيون للمرة الأولى منذ اندلاع الأزمة في البلاد, اجتماعا داخل مدينة عدن الجنوبية بعد تحريرها من سيطرة الميليشيات الحوثية والقوات الموالية للرئيس السابق علي عبد الله صالح، بينما تدور معارك شرسة لتطهير حي التواهي, آخر معاقل المتمردين في عدن والذي يضم القصر الرئاسي.\n\n وبحثت المجموعة الحكومية صباح أمس مع قيادة السلطة المحلية في محافظات عدن ولحج وأبين الأوضاع الأمنية. وحسب مصادر لـ«الشرق الأوسط»، فإن الاجتماع كرس لمناقشة تثبيت الأمن في مدينة عدن المدمرة بعد حوالي 3 أشهر من الحرب، والانتهاء من تصفية الجيوب المتبقية للميليشيات، بالإضافة إلى المهام الرئيسية التي ستنفذها المجموعة، وهي إعادة تأهيل مطار عدن الدولي والميناء، لفك الحصار عن المدينة وإدخال المساعدات الإنسانية. في غضون ذلك، أحرزت المقاومة الشعبية تقدما في محافظة شبوة، جنوب شرقي اليمن، على حساب قوات المتمردين وحلفائهم.\n\n وأكد مصدر قبلي في شبوة لـ«الشرق الأوسط» سيطرة قوات الرئيس اليمني عبد ربه منصور هادي والمقاومة الشعبية على 3 مواقع عسكرية مهمة في «اللواء 19»، وهي مواقع «سوق» و«بيت الضيافة» والجبل المطل على اللواء العسكري المرابط في بيحان، قبل سقوط اللواء بكامله في يد المقاومة. ومن شأن هذا التقدم أن يعزل قوات الحوثيين وصالح في محافظة شبوة، عن المحافظات الشمالية، مما يعني قطع الإمدادات عن تلك القوات.\n\n من جهة أخرى، أصدر الرئيس هادي، القائد الأعلى للقوات المسلحة والأمن، قرارا بتعيين العميد الركن عبد الرحيم أحمد سالم عتيق، قائدا للمنطقة العسكرية الثانية، بعد ترقيته إلى رتبة لواء، ويقع مقر قيادة المنطقة العسكرية الثانية في الجيش اليمني في مدينة المكلا، عاصمة محافظة حضرموت، بجنوب شرقي البلاد.\n\n ...المزيد",
        "entities": {
            "LOC": [
                "عدن",
                "التوا",
                "هي",
                "ولح",
                "ج",
                "وأبي",
                "ن",
                "شبوة",
                "اليمن",
                "شب",
                "وة",
                "الشرق الأوسط",
                "بيحان",
                "المكلا",
                "حضرموت"
            ],
            "PERS": [
                "علي عبد الله صالح",
                "عبد ربه منصور",
                "هادي",
                "عبد الرحيم أحمد سالم عتيق"
            ],
            "ORG": [
                "الشرق الأوسط",
                "الحوثيين",
                "وصالح"
            ],
            "MISC": [
                "بيت الضيافة"
            ]
        },
        "labeled_entities": [
            {
                "entity": "عدن",
                "label": "Neutral"
            },
            {
                "entity": "التوا",
                "label": "Neutral"
            },
            {
                "entity": "هي",
                "label": "Neutral"
            },
            {
                "entity": "ولح",
                "label": "Neutral"
            },
            {
                "entity": "ج",
                "label": "Neutral"
            },
            {
                "entity": "وأبي",
                "label": "Neutral"
            },
            {
                "entity": "ن",
                "label": "Neutral"
            },
            {
                "entity": "شبوة",
                "label": "Neutral"
            },
            {
                "entity": "اليمن",
                "label": "Neutral"
            },
            {
                "entity": "شب",
                "label": "Neutral"
            },
            {
                "entity": "وة",
                "label": "Neutral"
            },
            {
                "entity": "الشرق الأوسط",
                "label": "Neutral"
            },
            {
                "entity": "بيحان",
                "label": "Neutral"
            },
            {
                "entity": "المكلا",
                "label": "Neutral"
            },
            {
                "entity": "حضرموت",
                "label": "Neutral"
            },
            {
                "entity": "علي عبد الله صالح",
                "label": "Antagonist"
            },
            {
                "entity": "عبد ربه منصور",
                "label": "Protagonist"
            },
            {
                "entity": "هادي",
                "label": "Protagonist"
            },
            {
                "entity": "عبد الرحيم أحمد سالم عتيق",
                "label": "Neutral"
            },
            {
                "entity": "الشرق الأوسط",
                "label": "Neutral"
            },
            {
                "entity": "الحوثيين",
                "label": "Antagonist"
            },
            {
                "entity": "وصالح",
                "label": "Antagonist"
            },
            {
                "entity": "بيت الضيافة",
                "label": "Neutral"
            }
        ],
        "events": [
            {
                "subject": "أعضاء في الحكومة اليمنية ومسؤولون أمنيون",
                "action": "عقد",
                "object": "اجتماعا",
                "context": "داخل مدينة عدن الجنوبية بعد تحريرها من سيطرة الميليشيات الحوثية والقوات الموالية للرئيس السابق علي عبد الله صالح، وللمرة الأولى منذ اندلاع الأزمة في البلاد",
                "subject_role": "Unknown",
                "object_role": "Unknown"
            },
            {
                "subject": "معارك",
                "action": "تدور",
                "object": null,
                "context": "شرسة لتطهير حي التواهي, آخر معاقل المتمردين في عدن والذي يضم القصر الرئاسي",
                "subject_role": "Unknown",
                "object_role": "Unknown"
            },
            {
                "subject": "المجموعة الحكومية",
                "action": "بحث",
                "object": "الأوضاع الأمنية",
                "context": "صباح أمس مع قيادة السلطة المحلية في محافظات عدن ولحج وأبين",
                "subject_role": "Unknown",
                "object_role": "Unknown"
            },
            {
                "subject": "الاجتماع",
                "action": "كرس",
                "object": "مناقشة تثبيت الأمن في مدينة عدن المدمرة",
                "context": "بعد حوالي 3 أشهر من الحرب، والانتهاء من تصفية الجيوب المتبقية للميليشيات، بالإضافة إلى المهام الرئيسية التي ستنفذها المجموعة، وهي إعادة تأهيل مطار عدن الدولي والميناء، لفك الحصار عن المدينة وإدخال المساعدات الإنسانية",
                "subject_role": "Neutral",
                "object_role": "Unknown"
            },
            {
                "subject": "المقاومة الشعبية",
                "action": "أحرزت",
                "object": "تقدما",
                "context": "في محافظة شبوة، جنوب شرقي اليمن، على حساب قوات المتمردين وحلفائهم",
                "subject_role": "Unknown",
                "object_role": "Unknown"
            },
            {
                "subject": "قوات الرئيس اليمني عبد ربه منصور هادي والمقاومة الشعبية",
                "action": "سيطرة",
                "object": "3 مواقع عسكرية مهمة في «اللواء 19»",
                "context": "في شبوة",
                "subject_role": "Unknown",
                "object_role": "Unknown"
            },
            {
                "subject": "الرئيس هادي",
                "action": "أصدر",
                "object": "قرارا",
                "context": "بتعيين العميد الركن عبد الرحيم أحمد سالم عتيق، قائدا للمنطقة العسكرية الثانية، بعد ترقيته إلى رتبة لواء",
                "subject_role": "Unknown",
                "object_role": "Unknown"
            }
        ]
    },
    {
        "text": "سددت قوات الأمن السعودية ضربات قاصمة للإرهاب إثر تمكنها من تفكيك خلايا إرهابية «عنقودية» مرتبطة بتنظيم داعش وتدار من الخارج، خططت لاستهداف مساجد ومنشآت حكومية وأمنية، وبعثة دبلوماسية.\n\n وأعلنت وزارة الداخلية السعودية، أمس، القبض على 431 عنصرا أغلبهم سعوديون وبينهم أجانب من 9 جنسيات مختلفة، خططوا من المناطق المضطربة في دول الجوار لإثارة الفتنة الطائفية وإشاعة الفوضى وتفجير 7 مساجد في مدينتي الرياض والدمام خلال صلاة يوم الجمعة.\n\n وقال العميد بسام عطية, المسؤول في وزارة الداخلية خلال مؤتمر صحافي عقد في الرياض, أمس, إن تنظيم داعش اصبح بمثابة ميليشيات تقود حربا بالوكالة لصالح دول تستهدف السعودية.\n\n بدوره, أوضح اللواء منصور التركي، المتحدث الأمني في وزارة الداخلية السعودية، أن المقبوض عليهم، وبينهم عناصر يحملون الجنسية اليمنية والمصرية والسورية والأردنية والجزائرية والنيجيرية والتشادية، وآخرون غير محددي الهوية، شكلوا 4 خلايا إرهابية، بقيادة سعودي على تواصل مع «داعش» في سوريا، وأن التنظيم الإرهابي استغل نحو 40 امرأة إلى جانب أطفالهن لتنفيذ مخططاته.\n\n وحسب وزارة الداخلية السعودية فقد حدد لكل خلية دورها، إذ تشترك اثنتان منها في الرصد الميداني للمواقع المستهدفة، فيما تتولى الخلية الثالثة تجهيز الانتحاريين، أما الرابعة فكانت مهمتها تصنيع الأحزمة الناسفة.\n\n وقال اللواء التركي, خلال المؤتمر الصحافي، إن هذا التنظيم نفذ عددًا من العمليات الإجرامية شملت حادث استهداف المصلين بقرية الدالوة بمحافظة الأحساء، وإطلاق النار على دورية الأمن العام شرق مدينة الرياض، وحادث إطلاق النار على دورية لأمن المنشآت أثناء تأديتها عملها بمحيط موقع الخزن الاستراتيجي جنوب مدينة الرياض، وحادث استهداف المصلين بمسجد الإمام علي بن أبي طالب ببلدة القديح، واستهداف المصلين الفاشل بمسجد الحسين بن علي، بحي العنود بالدمام.\n\n وأكد المتحدث الأمني إحباط عمليات إرهابية مروعة خطط لها تنظيم داعش خلال أيام شهر رمضان، والبعض منها حدد لتنفيذها في التاسع من الشهر الفضيل، لتتزامن مع عمليات التنظيم الإرهابية التي نفذت في الكويت وتونس وفرنسا.\n\n ...المزيد",
        "entities": {
            "ORG": [
                "داعش"
            ],
            "LOC": [
                "الرياض",
                "والدم",
                "ام",
                "السعودية",
                "سوريا",
                "الدالوة",
                "الأحساء",
                "القديح",
                "العنود",
                "بالدمام",
                "الكويت",
                "وتونس",
                "وفرنسا"
            ],
            "PERS": [
                "بسام",
                "عطية",
                "منصور التركي",
                "علي بن أبي طالب",
                "الحسين بن علي"
            ]
        },
        "labeled_entities": [
            {
                "entity": "داعش",
                "label": "Antagonist"
            },
            {
                "entity": "الرياض",
                "label": "Neutral"
            },
            {
                "entity": "والدم",
                "label": "Neutral"
            },
            {
                "entity": "ام",
                "label": "Neutral"
            },
            {
                "entity": "السعودية",
                "label": "Protagonist"
            },
            {
                "entity": "سوريا",
                "label": "Neutral"
            },
            {
                "entity": "الدالوة",
                "label": "Neutral"
            },
            {
                "entity": "الأحساء",
                "label": "Neutral"
            },
            {
                "entity": "القديح",
                "label": "Neutral"
            },
            {
                "entity": "العنود",
                "label": "Neutral"
            },
            {
                "entity": "بالدمام",
                "label": "Neutral"
            },
            {
                "entity": "الكويت",
                "label": "Neutral"
            },
            {
                "entity": "وتونس",
                "label": "Neutral"
            },
            {
                "entity": "وفرنسا",
                "label": "Neutral"
            },
            {
                "entity": "بسام",
                "label": "Protagonist"
            },
            {
                "entity": "عطية",
                "label": "Protagonist"
            },
            {
                "entity": "منصور التركي",
                "label": "Protagonist"
            },
            {
                "entity": "علي بن أبي طالب",
                "label": "Neutral"
            },
            {
                "entity": "الحسين بن علي",
                "label": "Neutral"
            }
        ],
        "events": [
            {
                "subject": "قوات الأمن السعودية",
                "action": "سددت",
                "object": "ضربات",
                "context": "قاصمة للإرهاب",
                "subject_role": "Unknown",
                "object_role": "Unknown"
            },
            {
                "subject": "قوات الأمن السعودية",
                "action": "تمكنت",
                "object": "تفكيك",
                "context": "خلايا إرهابية «عنقودية» مرتبطة بتنظيم داعش",
                "subject_role": "Unknown",
                "object_role": "Unknown"
            },
            {
                "subject": "الخلايا الإرهابية",
                "action": "خططت",
                "object": "استهداف",
                "context": "مساجد ومنشآت حكومية وأمنية، وبعثة دبلوماسية",
                "subject_role": "Unknown",
                "object_role": "Unknown"
            },
            {
                "subject": "وزارة الداخلية السعودية",
                "action": "أعلنت",
                "object": "القبض",
                "context": "على 431 عنصرا أغلبهم سعوديون وبينهم أجانب من 9 جنسيات مختلفة",
                "subject_role": "Unknown",
                "object_role": "Unknown"
            },
            {
                "subject": "العناصر",
                "action": "خططوا",
                "object": "إثارة",
                "context": "الفتنة الطائفية وإشاعة الفوضى وتفجير 7 مساجد في مدينتي الرياض والدمام خلال صلاة يوم الجمعة",
                "subject_role": "Neutral",
                "object_role": "Unknown"
            },
            {
                "subject": "تنظيم داعش",
                "action": "أصبح",
                "object": "ميليشيات",
                "context": "تقود حربا بالوكالة لصالح دول تستهدف السعودية",
                "subject_role": "Unknown",
                "object_role": "Unknown"
            },
            {
                "subject": "المقبوض عليهم",
                "action": "شكلوا",
                "object": "خلايا",
                "context": "4 خلايا إرهابية",
                "subject_role": "Unknown",
                "object_role": "Unknown"
            },
            {
                "subject": "التنظيم الإرهابي",
                "action": "استغل",
                "object": "امرأة",
                "context": "نحو 40 امرأة إلى جانب أطفالهن لتنفيذ مخططاته",
                "subject_role": "Unknown",
                "object_role": "Unknown"
            },
            {
                "subject": "وزارة الداخلية السعودية",
                "action": "حدد",
                "object": "دور",
                "context": "لكل خلية دورها",
                "subject_role": "Unknown",
                "object_role": "Unknown"
            },
            {
                "subject": "اثنتان منها",
                "action": "تشترك",
                "object": "الرصد",
                "context": "في الرصد الميداني للمواقع المستهدفة",
                "subject_role": "Unknown",
                "object_role": "Neutral"
            },
            {
                "subject": "الخلية الثالثة",
                "action": "تتولى",
                "object": "تجهيز",
                "context": "تجهيز الانتحاريين",
                "subject_role": "Unknown",
                "object_role": "Unknown"
            },
            {
                "subject": "الرابعة",
                "action": "كانت مهمتها",
                "object": "تصنيع",
                "context": "تصنيع الأحزمة الناسفة",
                "subject_role": "Neutral",
                "object_role": "Unknown"
            },
            {
                "subject": "التنظيم",
                "action": "نفذ",
                "object": "عمليات",
                "context": "عددًا من العمليات الإجرامية شملت حادث استهداف المصلين بقرية الدالوة بمحافظة الأحساء، وإطلاق النار على دورية الأمن العام شرق مدينة الرياض، وحادث إطلاق النار على دورية لأمن المنشآت أثناء تأديتها عملها بمحيط موقع الخزن الاستراتيجي جنوب مدينة الرياض، وحادث استهداف المصلين بمسجد الإمام علي بن أبي طالب ببلدة القديح، واستهداف المصلين الفاشل بمسجد الحسين بن علي، بحي العنود بالدمام",
                "subject_role": "Unknown",
                "object_role": "Unknown"
            },
            {
                "subject": "المتحدث الأمني",
                "action": "أكد",
                "object": "إحباط",
                "context": "عمليات إرهابية مروعة خطط لها تنظيم داعش خلال أيام شهر رمضان",
                "subject_role": "Unknown",
                "object_role": "Unknown"
            },
            {
                "subject": "عمليات",
                "action": "حدد",
                "object": "تنفيذ",
                "context": "البعض منها حدد لتنفيذها في التاسع من الشهر الفضيل، لتتزامن مع عمليات التنظيم الإرهابية التي نفذت في الكويت وتونس وفرنسا",
                "subject_role": "Unknown",
                "object_role": "Unknown"
            }
        ]
    },
    {
        "text": "صعد المرشد الأعلى الإيراني آية الله علي خامنئي من لهجته ضد الولايات المتحدة، أمس، موضحًا موقفه من أن الاتفاق النووي الإيراني لن يغير من العلاقات بين البلدين. وقال خامنئي في خطبة بمناسبة عيد الفطر في طهران، أمس: «قلنا مرارًا إننا لا نتفاوض مع الولايات المتحدة بشأن الشؤون الإقليمية أو الدولية ولا حتى القضايا الثنائية. هناك بعض الاستثناءات مثل البرنامج النووي الذي تفاوضنا عليه مع الأميركيين لخدمة مصالحنا». وأضاف: «لن نكف مطلقًا عن دعم أصدقائنا في المنطقة وشعوب فلسطين واليمن وسوريا والعراق والبحرين ولبنان. حتى بعد هذا الاتفاق لن تتغير سياستنا تجاه الولايات المتحدة المتغطرسة».\n\n بدوره، يسعى الرئيس الإيراني حسن روحاني إلى التظاهر بالانفتاح على المنطقة. وقال عقب اتصال هاتفي مع أمير قطر الشيخ تميم بن حمد آل ثاني «ما من شك في أن الاتفاق سيقود إلى علاقات أوثق مع الجيران خاصة قطر».\n\n وتبدو طهران منفتحة أيضًا على الجانب الأوروبي الذي يتوافد إليها سعيًا للحصول على عقود تجارية مثمرة فور رفع العقوبات الدولية عنها بموجب الاتفاق النووي.\n\n ويتوجه زيجمار جابريل، وزير الاقتصاد الألماني، اليوم، إلى طهران بصحبة وفد اقتصادي, بينما أعلن وزير الخارجية النمساوي، سباستيان كورتس، عزمه زيارة إيران في سبتمبر (أيلول) ، كما تستطلع لندن وباريس آفاق الفرص الاستثمارية في طهران.\n\n ...المزيد",
        "entities": {
            "PERS": [
                "آية الله علي خامنئي",
                "خامنئي",
                "حسن روحاني",
                "تميم بن حمد آل ثاني",
                "زي",
                "جمار جابريل",
                "سبا",
                "ستيان كورتس"
            ],
            "LOC": [
                "الولايات المتحدة",
                "طهران",
                "فلسطين",
                "واليمن",
                "وسوريا",
                "والعراق",
                "والبحرين",
                "ولبنان",
                "قطر",
                "إيران",
                "لندن",
                "وبار",
                "يس"
            ]
        },
        "labeled_entities": [
            {
                "entity": "آية الله علي خامنئي",
                "label": "Protagonist"
            },
            {
                "entity": "خامنئي",
                "label": "Protagonist"
            },
            {
                "entity": "حسن روحاني",
                "label": "Protagonist"
            },
            {
                "entity": "تميم بن حمد آل ثاني",
                "label": "Neutral"
            },
            {
                "entity": "زي",
                "label": "Neutral"
            },
            {
                "entity": "جمار جابريل",
                "label": "Neutral"
            },
            {
                "entity": "سبا",
                "label": "Neutral"
            },
            {
                "entity": "ستيان كورتس",
                "label": "Neutral"
            },
            {
                "entity": "الولايات المتحدة",
                "label": "Antagonist"
            },
            {
                "entity": "طهران",
                "label": "Protagonist"
            },
            {
                "entity": "فلسطين",
                "label": "Protagonist"
            },
            {
                "entity": "واليمن",
                "label": "Protagonist"
            },
            {
                "entity": "وسوريا",
                "label": "Protagonist"
            },
            {
                "entity": "والعراق",
                "label": "Protagonist"
            },
            {
                "entity": "والبحرين",
                "label": "Protagonist"
            },
            {
                "entity": "ولبنان",
                "label": "Protagonist"
            },
            {
                "entity": "قطر",
                "label": "Neutral"
            },
            {
                "entity": "إيران",
                "label": "Protagonist"
            },
            {
                "entity": "لندن",
                "label": "Neutral"
            },
            {
                "entity": "وبار",
                "label": "Neutral"
            },
            {
                "entity": "يس",
                "label": "Neutral"
            }
        ],
        "events": [
            {
                "subject": "آية الله علي خامنئي",
                "action": "صعد",
                "object": "لهجته",
                "context": "ضد الولايات المتحدة",
                "subject_role": "Protagonist",
                "object_role": "Unknown"
            },
            {
                "subject": "آية الله علي خامنئي",
                "action": "أوضح",
                "object": "موقفه",
                "context": "الاتفاق النووي الإيراني لن يغير من العلاقات بين البلدين",
                "subject_role": "Protagonist",
                "object_role": "Unknown"
            },
            {
                "subject": "خامنئي",
                "action": "قال",
                "object": null,
                "context": "لا نتفاوض مع الولايات المتحدة بشأن الشؤون الإقليمية أو الدولية",
                "subject_role": "Protagonist",
                "object_role": "Unknown"
            },
            {
                "subject": "خامنئي",
                "action": "قال",
                "object": null,
                "context": "تفاوضنا على البرنامج النووي مع الأميركيين لخدمة مصالحنا",
                "subject_role": "Protagonist",
                "object_role": "Unknown"
            },
            {
                "subject": "خامنئي",
                "action": "أضاف",
                "object": null,
                "context": "لن نكف مطلقًا عن دعم أصدقائنا في المنطقة وشعوب فلسطين واليمن وسوريا والعراق والبحرين ولبنان",
                "subject_role": "Protagonist",
                "object_role": "Unknown"
            },
            {
                "subject": "خامنئي",
                "action": "أضاف",
                "object": null,
                "context": "لن تتغير سياستنا تجاه الولايات المتحدة المتغطرسة",
                "subject_role": "Protagonist",
                "object_role": "Unknown"
            },
            {
                "subject": "حسن روحاني",
                "action": "يسعى",
                "object": null,
                "context": "التظاهر بالانفتاح على المنطقة",
                "subject_role": "Protagonist",
                "object_role": "Unknown"
            },
            {
                "subject": "حسن روحاني",
                "action": "قال",
                "object": null,
                "context": "الاتفاق سيقود إلى علاقات أوثق مع الجيران خاصة قطر",
                "subject_role": "Protagonist",
                "object_role": "Unknown"
            },
            {
                "subject": "طهران",
                "action": "تبدو",
                "object": null,
                "context": "منفتحة على الجانب الأوروبي",
                "subject_role": "Protagonist",
                "object_role": "Unknown"
            },
            {
                "subject": "زيجمار جابريل",
                "action": "يتوجه",
                "object": "إيران",
                "context": "اليوم بصحبة وفد اقتصادي",
                "subject_role": "Neutral",
                "object_role": "Protagonist"
            },
            {
                "subject": "سباستيان كورتس",
                "action": "أعلن",
                "object": "عزمه زيارة إيران",
                "context": "في سبتمبر",
                "subject_role": "Neutral",
                "object_role": "Unknown"
            },
            {
                "subject": "لندن",
                "action": "تستطلع",
                "object": "آفاق الفرص الاستثمارية",
                "context": "في طهران",
                "subject_role": "Neutral",
                "object_role": "Unknown"
            },
            {
                "subject": "باريس",
                "action": "تستطلع",
                "object": "آفاق الفرص الاستثمارية",
                "context": "في طهران",
                "subject_role": "Neutral",
                "object_role": "Unknown"
            }
        ]
    },
    {
        "text": "شيع النظام السوري أمس جثمان اللواء محسن مخلوف، قائد الفرقة 11 دبابات وقريب والدة رئيس النظام السوري بشار الأسد في اللاذقية، الذي كان مكلفًا عملية استعادة السيطرة على مدينة تدمر ومحيطها.\n\n وأفاد «المرصد السوري لحقوق الإنسان» بأن مخلوف «قُتل جراء استهدافه من قبل تنظيم داعش في ريف محافظة حمص الشرقي عندما كان عائدًا من جولة تفقدية على عناصره، على جبهات القتال في منطقة تدمر. كما تمكن التنظيم في اليوم ذاته من قتل 4 ضباط آخرين برتب عميد وعقيد، و12 عنصرًا آخر من قوات النظام بينهم ضباط صف».\n\n ويُعتبر اللواء محسن مخلوف أرفع ضابط في قوات النظام قتل منذ مقتل اللواء محيي الدين منصور، قائد «القوات الخاصة» في سوريا في أوائل مايو (أيار) من العام الحالي.\n\n في غضون ذلك، أفادت صحيفة «التايمز» البريطانية بفرار مئات الضباط في الجيش السوري بينهم مقربون من الأسد. ونقلت الصحيفة عن مواقع سورية معارضة، أن 686 عسكريا من القرداحة، مسقط رأس عائلة الأسد، في محافظة اللاذقية، هربوا من الجيش خلال الستة أشهر الأولى من هذا العام، وأغلبهم ضباط وقادة كبار.\n\n وأضافت الصحيفة أن 14 من الهاربين ينتمون إلى عائلة مخلوف.\n\n ...المزيد",
        "entities": {
            "PERS": [
                "محسن مخلوف",
                "بشار الأسد",
                "مخ",
                "لوف",
                "محي",
                "ي الدين منصور",
                "الأسد"
            ],
            "LOC": [
                "اللاذقية",
                "تدمر",
                "حمص",
                "سوريا",
                "القرداحة"
            ],
            "ORG": [
                "المرصد",
                "داعش",
                "التايمز"
            ]
        },
        "labeled_entities": [
            {
                "entity": "محسن مخلوف",
                "label": "Neutral"
            },
            {
                "entity": "بشار الأسد",
                "label": "Neutral"
            },
            {
                "entity": "مخ",
                "label": "Neutral"
            },
            {
                "entity": "لوف",
                "label": "Neutral"
            },
            {
                "entity": "محي",
                "label": "Neutral"
            },
            {
                "entity": "ي الدين منصور",
                "label": "Neutral"
            },
            {
                "entity": "الأسد",
                "label": "Neutral"
            },
            {
                "entity": "اللاذقية",
                "label": "Neutral"
            },
            {
                "entity": "تدمر",
                "label": "Neutral"
            },
            {
                "entity": "حمص",
                "label": "Neutral"
            },
            {
                "entity": "سوريا",
                "label": "Neutral"
            },
            {
                "entity": "القرداحة",
                "label": "Neutral"
            },
            {
                "entity": "المرصد",
                "label": "Neutral"
            },
            {
                "entity": "داعش",
                "label": "Antagonist"
            },
            {
                "entity": "التايمز",
                "label": "Neutral"
            }
        ],
        "events": [
            {
                "subject": "النظام السوري",
                "action": "شيع",
                "object": "جثمان",
                "context": "جثمان اللواء محسن مخلوف في اللاذقية",
                "subject_role": "Unknown",
                "object_role": "Unknown"
            },
            {
                "subject": "محسن مخلوف",
                "action": "كان مكلفا",
                "object": "عملية",
                "context": "عملية استعادة السيطرة على مدينة تدمر ومحيطها",
                "subject_role": "Neutral",
                "object_role": "Unknown"
            },
            {
                "subject": "محسن مخلوف",
                "action": "قتل",
                "object": null,
                "context": "قُتل جراء استهدافه من قبل تنظيم داعش في ريف محافظة حمص الشرقي",
                "subject_role": "Neutral",
                "object_role": "Unknown"
            },
            {
                "subject": "تنظيم داعش",
                "action": "استهدف",
                "object": "محسن مخلوف",
                "context": "في ريف محافظة حمص الشرقي",
                "subject_role": "Unknown",
                "object_role": "Neutral"
            },
            {
                "subject": "التنظيم",
                "action": "تمكن",
                "object": "قتل",
                "context": "تمكن من قتل 4 ضباط آخرين برتب عميد وعقيد، و12 عنصرًا آخر من قوات النظام بينهم ضباط صف",
                "subject_role": "Neutral",
                "object_role": "Unknown"
            },
            {
                "subject": "محسن مخلوف",
                "action": "يعتبر",
                "object": "ضابط",
                "context": "أرفع ضابط في قوات النظام قتل منذ مقتل اللواء محيي الدين منصور",
                "subject_role": "Neutral",
                "object_role": "Unknown"
            },
            {
                "subject": "محيي الدين منصور",
                "action": "قتل",
                "object": null,
                "context": "في أوائل مايو (أيار) من العام الحالي",
                "subject_role": "Neutral",
                "object_role": "Unknown"
            },
            {
                "subject": "ضباط",
                "action": "فر",
                "object": null,
                "context": "مئات الضباط في الجيش السوري بينهم مقربون من الأسد",
                "subject_role": "Unknown",
                "object_role": "Unknown"
            },
            {
                "subject": "عسكريا",
                "action": "هربوا",
                "object": null,
                "context": "686 عسكريا من القرداحة هربوا من الجيش خلال الستة أشهر الأولى من هذا العام",
                "subject_role": "Neutral",
                "object_role": "Unknown"
            },
            {
                "subject": "14",
                "action": "ينتمون",
                "object": null,
                "context": "14 من الهاربين ينتمون إلى عائلة مخلوف",
                "subject_role": "Unknown",
                "object_role": "Unknown"
            }
        ]
    },
    {
        "text": "تفحص السلطات المالية الأميركية سلوك عدد من الشركات التي لها ارتباطات مع الاتحاد الدولي لكرة القدم (فيفا) أو أي اتحادات أو جهات كروية ارتبط اسمها بفضيحة الفساد، وذلك لمعرفة ما إذا كانت هناك خروقات للقوانين الأميركية الفيدرالية المتعلقة بتلقي رشى.\n\n وطبقا لمصدر مطلع، فإن هذا التحقيق ستجريه لجنة الأوراق المالية والبورصات الأميركية، وسيعد بمثابة فتح جبهة جديدة في التحقيقات الواسعة التي تباشرها السلطات الأميركية والسويسرية حول قضايا تتعلق برشى تضم مسؤولين كرويين وآخرين تنفيذيين في مجال الإعلام والترويج الرياضي. وطبقا للمصدر، الذي رفض الإفصاح عن اسمه لأسباب تتعلق بسرية التحقيقات، فإن لجنة الأوراق المالية والبورصات الأميركية سوف تركز على الشركات التجارية التي انخرطت في عقود كروية مثل شركة «نايكي».\n\n من جهة أخرى، أكد مدعي عام نيويورك أن جيفري ويب، النائب السابق لرئيس الفيفا، مثل أمام المحكمة في نيويورك أمس. وكان ويب، وهو من جزر كايمان، وصل إلى الولايات المتحدة الأربعاء الماضي بعد أن وافق على تسليمه إلى السلطات الأميركية حيث كان معتقلا في سويسرا بتهم فساد. كما ألقي القبض أمس على رئيس الاتحاد البوليفي لكرة القدم وأمين صندوق اتحاد أميركا الجنوبية كارلوس شافيز بالتهم نفسها.\n\n في غضون ذلك، تجتمع اللجنة التنفيذية في الفيفا غدا بمدينة زيوريخ السويسرية لتحديد موعد لانتخاب رئيس جديد يخلف الرئيس المستقيل سيب بلاتر.\n\n ...المزيد",
        "entities": {
            "ORG": [
                "الاتحاد الدولي لكرة القدم",
                "فيفا",
                "نايكي",
                "الفيفا",
                "الاتحاد البوليفي لكرة القدم",
                "اتحاد أميركا الجنوبية"
            ],
            "LOC": [
                "نيويورك",
                "جزر كايمان",
                "الولايات المتحدة",
                "سويسرا",
                "زيوريخ"
            ],
            "PERS": [
                "جيفري ويب",
                "ويب",
                "كارلوس شافيز",
                "سيب بلاتر"
            ]
        },
        "labeled_entities": [
            {
                "entity": "الاتحاد الدولي لكرة القدم",
                "label": "Antagonist"
            },
            {
                "entity": "فيفا",
                "label": "Antagonist"
            },
            {
                "entity": "نايكي",
                "label": "Neutral"
            },
            {
                "entity": "الفيفا",
                "label": "Antagonist"
            },
            {
                "entity": "الاتحاد البوليفي لكرة القدم",
                "label": "Antagonist"
            },
            {
                "entity": "اتحاد أميركا الجنوبية",
                "label": "Antagonist"
            },
            {
                "entity": "نيويورك",
                "label": "Neutral"
            },
            {
                "entity": "جزر كايمان",
                "label": "Neutral"
            },
            {
                "entity": "الولايات المتحدة",
                "label": "Protagonist"
            },
            {
                "entity": "سويسرا",
                "label": "Neutral"
            },
            {
                "entity": "زيوريخ",
                "label": "Neutral"
            },
            {
                "entity": "جيفري ويب",
                "label": "Antagonist"
            },
            {
                "entity": "ويب",
                "label": "Antagonist"
            },
            {
                "entity": "كارلوس شافيز",
                "label": "Antagonist"
            },
            {
                "entity": "سيب بلاتر",
                "label": "Antagonist"
            }
        ],
        "events": [
            {
                "subject": "السلطات المالية الأميركية",
                "action": "تفحص",
                "object": "سلوك",
                "context": "عدد من الشركات التي لها ارتباطات مع الاتحاد الدولي لكرة القدم (فيفا) أو أي اتحادات أو جهات كروية ارتبط اسمها بفضيحة الفساد",
                "subject_role": "Unknown",
                "object_role": "Unknown"
            },
            {
                "subject": "لجنة الأوراق المالية والبورصات الأميركية",
                "action": "ستجري",
                "object": "التحقيق",
                "context": "هذا",
                "subject_role": "Unknown",
                "object_role": "Unknown"
            },
            {
                "subject": "لجنة الأوراق المالية والبورصات الأميركية",
                "action": "سوف تركز",
                "object": null,
                "context": "على الشركات التجارية التي انخرطت في عقود كروية مثل شركة «نايكي»",
                "subject_role": "Unknown",
                "object_role": "Unknown"
            },
            {
                "subject": "جيفري ويب",
                "action": "مثل",
                "object": "المحكمة",
                "context": "في نيويورك أمس",
                "subject_role": "Antagonist",
                "object_role": "Unknown"
            },
            {
                "subject": "ويب",
                "action": "وصل",
                "object": "الولايات المتحدة",
                "context": "الأربعاء الماضي",
                "subject_role": "Antagonist",
                "object_role": "Protagonist"
            },
            {
                "subject": "ويب",
                "action": "وافق",
                "object": "تسليمه",
                "context": "إلى السلطات الأميركية",
                "subject_role": "Antagonist",
                "object_role": "Unknown"
            },
            {
                "subject": "ويب",
                "action": "كان معتقلا",
                "object": null,
                "context": "في سويسرا بتهم فساد",
                "subject_role": "Antagonist",
                "object_role": "Unknown"
            },
            {
                "subject": "رئيس الاتحاد البوليفي لكرة القدم وأمين صندوق اتحاد أميركا الجنوبية كارلوس شافيز",
                "action": "ألقي القبض",
                "object": null,
                "context": "أمس بالتهم نفسها",
                "subject_role": "Unknown",
                "object_role": "Unknown"
            },
            {
                "subject": "اللجنة التنفيذية",
                "action": "تجتمع",
                "object": null,
                "context": "في الفيفا غدا بمدينة زيوريخ السويسرية",
                "subject_role": "Unknown",
                "object_role": "Unknown"
            },
            {
                "subject": "اللجنة التنفيذية",
                "action": "تحديد",
                "object": "موعد",
                "context": "لانتخاب رئيس جديد يخلف الرئيس المستقيل سيب بلاتر",
                "subject_role": "Unknown",
                "object_role": "Unknown"
            }
        ]
    },
    {
        "text": "بعد تحرير المقاومة الموالية للحكومة اليمنية الشرعية لمدينة عدن، قالت مصادر محلية أمس إن المقاومة تعد الآن لتحرير «قاعدة العند» العسكرية الاستراتيجية، وهي قاعدة تبعد نحو 60 كيلومترا شمال عدن، وتتبع إداريا لمحافظة لحج المجاورة. وأكد شهود عيان لـ«الشرق الأوسط»، أمس، أن طيران التحالف نفذ سلسلة من الغارات الجوية على القاعدة العسكرية والمناطق المجاورة لها.\n\n في غضون ذلك، قالت مصادر مطلعة لـ«الشرق الأوسط» إن وفد الحكومة الذي عاد إلى عدن أمس ويضم وزراء ومسؤولين أمنيين «سيعمل على إيجاد موقع قدم لانطلاق العمل الحكومي من عدن، ثم تليها بقية المحافظات حسب أهداف مشروع السهم الذهبي».\n\n وفي مؤشر على استئناف العمل الحكومي والإداري، كشف اللواء جعفر محمد سعد، مستشار الرئيس اليمني عبد ربه منصور هادي، في تصريحات لـ«الشرق الأوسط»، أنه «تم استئناف فتح جميع مديريات الشرطة في عدن، وتم تكوين قوة خاصة لملاحقة المجرمين، وبعض بقايا المتمردين في حال ثبت وجودهم بين المدنيين»، مضيفا أن مديريات الشرطة باشرت أعمالها بقيادة العميد محمد مساعد ابتداء من يوم أمس.\n\n وأوضح اللواء محمد سعد، من ناحية أخرى، أن المقاومة الشعبية أسرت أمس 45 حوثيا، وكانت تحاصر 35 آخرين في منطقتي خور مكسر وكريتر بعدن. وأضاف أن المقاومة قدمت ضمانات للميليشيات الحوثية حتى تغادر عدن، وتوفر وسيلة نقل لها، إلا أن 30 مقاتلا منها بقوا متحصنين في فندق مركيور بخور مكسر، وخمسة آخرين في بناية سكنية في كريتر.\n\n وتابع قائلا: «المحاصرون من الميليشيات الحوثية وأتباع الرئيس السابق علي عبد الله صالح، يعيشون حاليا تحت أحلام قياداتهم المتمردة، مع وعود بإرسال تعزيزات وقوة عسكرية لمساعدتهم، واستعادة عدن، إلا أنهم أصبحوا ضحية هذه الأحلام والأوهام».\n\n ...المزيد",
        "entities": {
            "LOC": [
                "عدن",
                "العند",
                "لحج",
                "خور مكسر",
                "وكريتر",
                "بعد",
                "ن",
                "ور مكسر",
                "كري",
                "تر"
            ],
            "ORG": [
                "الشرق الأوسط",
                "مرك",
                "بخ"
            ],
            "PERS": [
                "جعفر محمد سعد",
                "عبد ربه منصور هادي",
                "محمد مساعد",
                "محمد سعد",
                "علي عبد الله صالح"
            ],
            "MISC": [
                "يور"
            ]
        },
        "labeled_entities": [
            {
                "entity": "عدن",
                "label": "Neutral"
            },
            {
                "entity": "العند",
                "label": "Neutral"
            },
            {
                "entity": "لحج",
                "label": "Neutral"
            },
            {
                "entity": "خور مكسر",
                "label": "Neutral"
            },
            {
                "entity": "وكريتر",
                "label": "Neutral"
            },
            {
                "entity": "بعد",
                "label": "Neutral"
            },
            {
                "entity": "ن",
                "label": "Neutral"
            },
            {
                "entity": "ور مكسر",
                "label": "Neutral"
            },
            {
                "entity": "كري",
                "label": "Neutral"
            },
            {
                "entity": "تر",
                "label": "Neutral"
            },
            {
                "entity": "الشرق الأوسط",
                "label": "Neutral"
            },
            {
                "entity": "مرك",
                "label": "Neutral"
            },
            {
                "entity": "بخ",
                "label": "Neutral"
            },
            {
                "entity": "جعفر محمد سعد",
                "label": "Protagonist"
            },
            {
                "entity": "عبد ربه منصور هادي",
                "label": "Protagonist"
            },
            {
                "entity": "محمد مساعد",
                "label": "Protagonist"
            },
            {
                "entity": "محمد سعد",
                "label": "Protagonist"
            },
            {
                "entity": "علي عبد الله صالح",
                "label": "Antagonist"
            },
            {
                "entity": "يور",
                "label": "Neutral"
            }
        ],
        "events": [
            {
                "subject": "المقاومة الموالية للحكومة اليمنية الشرعية",
                "action": "حررت",
                "object": "مدينة عدن",
                "subject_role": "Unknown",
                "object_role": "Unknown"
            },
            {
                "subject": "مصادر محلية",
                "action": "قالت",
                "object": null,
                "context": "المقاومة تعد الآن لتحرير «قاعدة العند» العسكرية الاستراتيجية",
                "subject_role": "Unknown",
                "object_role": "Unknown"
            },
            {
                "subject": "طيران التحالف",
                "action": "نفذ",
                "object": "سلسلة من الغارات الجوية",
                "context": "على القاعدة العسكرية والمناطق المجاورة لها",
                "subject_role": "Unknown",
                "object_role": "Unknown"
            },
            {
                "subject": "وفد الحكومة",
                "action": "سيعمل",
                "object": null,
                "context": "على إيجاد موقع قدم لانطلاق العمل الحكومي من عدن، ثم تليها بقية المحافظات حسب أهداف مشروع السهم الذهبي",
                "subject_role": "Unknown",
                "object_role": "Unknown"
            },
            {
                "subject": "اللواء جعفر محمد سعد",
                "action": "كشف",
                "object": null,
                "context": "تم استئناف فتح جميع مديريات الشرطة في عدن، وتم تكوين قوة خاصة لملاحقة المجرمين، وبعض بقايا المتمردين",
                "subject_role": "Protagonist",
                "object_role": "Unknown"
            },
            {
                "subject": "مديريات الشرطة",
                "action": "باشرت",
                "object": "أعمالها",
                "context": "بقيادة العميد محمد مساعد",
                "subject_role": "Unknown",
                "object_role": "Unknown"
            },
            {
                "subject": "المقاومة الشعبية",
                "action": "أسرت",
                "object": "45 حوثيا",
                "context": "في منطقتي خور مكسر وكريتر بعدن",
                "subject_role": "Unknown",
                "object_role": "Unknown"
            },
            {
                "subject": "المقاومة الشعبية",
                "action": "تحاصر",
                "object": "35 آخرين",
                "context": "في منطقتي خور مكسر وكريتر بعدن",
                "subject_role": "Unknown",
                "object_role": "Unknown"
            },
            {
                "subject": "المقاومة",
                "action": "قدمت",
                "object": "ضمانات",
                "context": "للميليشيات الحوثية حتى تغادر عدن، وتوفر وسيلة نقل لها",
                "subject_role": "Unknown",
                "object_role": "Unknown"
            },
            {
                "subject": "مقاتلون",
                "action": "بقوا",
                "object": "متحصنين",
                "context": "في فندق مركيور بخور مكسر",
                "subject_role": "Unknown",
                "object_role": "Unknown"
            },
            {
                "subject": "مقاتلون",
                "action": "بقوا",
                "object": "متحصنين",
                "context": "في بناية سكنية في كريتر",
                "subject_role": "Unknown",
                "object_role": "Unknown"
            },
            {
                "subject": "المحاصرون",
                "action": "يعيشون",
                "object": null,
                "context": "تحت أحلام قياداتهم المتمردة، مع وعود بإرسال تعزيزات وقوة عسكرية لمساعدتهم، واستعادة عدن",
                "subject_role": "Unknown",
                "object_role": "Unknown"
            }
        ]
    },
    {
        "text": "يسعى المحققون الأميركيون لتحديد السبب الذي دفع بالشاب الأردني الكويتي المولد محمد يوسف عبد العزيز (24 عاما) الذي كان يعيش في ولاية تينيسي، إلى إطلاق النار على مركزين عسكريين في مدينة تشاتانوغا التابعة للولاية، مساء أول من أمس، مما أدى إلى مقتل أربعة من المارينز وإصابة ثلاثة أشخاص، قبل أن يقتل هو بالرصاص. وبينما يركز المحققون على سفره إلى الأردن العام الماضي، لمعرفة ما إذا كان اتصل حينها بمتطرفين، قالت الشرطة إنها تتعامل مع القضية التي تذكر بهجمات أخرى مشابهة تعرضت لها منشآت عسكرية أميركية، على أنها قضية «إرهاب داخلي». ورغم أن السلطات لم تعرف الدافع وراء الهجوم على الفور، فإن الحادثة أثارت مخاوف من أن يكون عبد العزيز واحدًا ممن يطلق عليهم وصف «الذئاب المنفردة»، أي أنه يعمل بمفرده ولا ينتمي إلى أي جماعة متشددة.\n\n وتفيد المعلومات المتداولة بأن عبد العزيز كتب في دليل تخرج طلاب ثانوية «ريد رانك» ، في تشاتانوغا قبل أربعة أعوام: «اسمي سيحدث هلعًا في كل أرجاء الولايات المتحدة. ماذا سيحدث اسمك؟».\n\n ...المزيد",
        "entities": {
            "PERS": [
                "محمد يوسف عبد العزيز",
                "عبد العزيز"
            ],
            "LOC": [
                "تينيسي",
                "تشاتانوغا",
                "الأردن",
                "تشا",
                "تانوغا",
                "الولايات المتحدة"
            ],
            "ORG": [
                "ريد رانك"
            ]
        },
        "labeled_entities": [
            {
                "entity": "محمد يوسف عبد العزيز",
                "label": "Antagonist"
            },
            {
                "entity": "عبد العزيز",
                "label": "Antagonist"
            },
            {
                "entity": "تينيسي",
                "label": "Neutral"
            },
            {
                "entity": "تشاتانوغا",
                "label": "Neutral"
            },
            {
                "entity": "الأردن",
                "label": "Neutral"
            },
            {
                "entity": "تشا",
                "label": "Neutral"
            },
            {
                "entity": "تانوغا",
                "label": "Neutral"
            },
            {
                "entity": "الولايات المتحدة",
                "label": "Protagonist"
            },
            {
                "entity": "ريد رانك",
                "label": "Neutral"
            }
        ],
        "events": [
            {
                "subject": "المحققون الأميركيون",
                "action": "يسعى",
                "object": "تحديد السبب",
                "context": "الذي دفع بالشاب الأردني الكويتي المولد محمد يوسف عبد العزيز (24 عاما) الذي كان يعيش في ولاية تينيسي",
                "subject_role": "Unknown",
                "object_role": "Unknown"
            },
            {
                "subject": "محمد يوسف عبد العزيز",
                "action": "أطلق النار",
                "object": "مركزين عسكريين",
                "context": "في مدينة تشاتانوغا التابعة للولاية، مساء أول من أمس",
                "subject_role": "Antagonist",
                "object_role": "Unknown"
            },
            {
                "subject": "إطلاق النار",
                "action": "أدى",
                "object": "مقتل أربعة من المارينز",
                "context": "وإصابة ثلاثة أشخاص",
                "subject_role": "Unknown",
                "object_role": "Unknown"
            },
            {
                "subject": "محمد يوسف عبد العزيز",
                "action": "قتل",
                "object": "الرصاص",
                "context": "قبل أن يقتل هو",
                "subject_role": "Antagonist",
                "object_role": "Unknown"
            },
            {
                "subject": "المحققون",
                "action": "يركز",
                "object": "سفره",
                "context": "إلى الأردن العام الماضي، لمعرفة ما إذا كان اتصل حينها بمتطرفين",
                "subject_role": "Unknown",
                "object_role": "Unknown"
            },
            {
                "subject": "الشرطة",
                "action": "تتعامل",
                "object": "القضية",
                "context": "على أنها قضية «إرهاب داخلي»",
                "subject_role": "Unknown",
                "object_role": "Unknown"
            },
            {
                "subject": "الحادثة",
                "action": "أثارت",
                "object": "مخاوف",
                "context": "من أن يكون عبد العزيز واحدًا ممن يطلق عليهم وصف «الذئاب المنفردة»",
                "subject_role": "Unknown",
                "object_role": "Unknown"
            },
            {
                "subject": "عبد العزيز",
                "action": "كتب",
                "object": "دليل تخرج",
                "context": "طلاب ثانوية «ريد رانك» ، في تشاتانوغا قبل أربعة أعوام",
                "subject_role": "Antagonist",
                "object_role": "Unknown"
            },
            {
                "subject": "اسمي",
                "action": "سيحدث",
                "object": "هلعًا",
                "context": "في كل أرجاء الولايات المتحدة",
                "subject_role": "Unknown",
                "object_role": "Unknown"
            }
        ]
    },
    {
        "text": "في خطوة عدها محللون محاولة من خصوم الرئيس الأميركي لعرقلة «الاتفاق النووي الإيراني»، طلب عدد من المشرعين من الحزبين، من الرئيس باراك أوباما، تأجيل التصويت على الاتفاق المفترض أن يجري الاثنين. وقال السيناتوران الجمهوري بوب كروكر، والديمقراطي بنجامين كاردين، في خطاب مشترك, إن «الأمر يتطلب إرجاء نظر الأمم المتحدة في الاتفاق حتى يتمكن الكونغرس من النظر فيه والتصويت عليه».\n\n في غضون ذلك، دافع وزير الخارجية الأميركي جون كيري أمس عن مهلة الـ 24 يوماً التي يمنحها الاتفاق لطهران، عندما ترغب الوكالة الدولية للطاقة الذرية في تفتيش مواقعها. وقال «أجهزتنا الاستخباراتية مرتاحة بشأن فترة الـ24 يوما لإنها ليست كافية ليتمكنوا من تجنب طرقنا الفنية وقدرتنا على المراقبة».\n\n ...المزيد",
        "entities": {
            "PERS": [
                "باراك أوباما",
                "بوب كروكر",
                "بنجامين كاردين",
                "جون كيري"
            ],
            "ORG": [
                "الأمم المتحدة",
                "الكونغرس",
                "الوكالة الدولية للطاقة الذرية"
            ],
            "LOC": [
                "لط",
                "هران"
            ]
        },
        "labeled_entities": [
            {
                "entity": "باراك أوباما",
                "label": "Neutral"
            },
            {
                "entity": "بوب كروكر",
                "label": "Antagonist"
            },
            {
                "entity": "بنجامين كاردين",
                "label": "Antagonist"
            },
            {
                "entity": "جون كيري",
                "label": "Protagonist"
            },
            {
                "entity": "الأمم المتحدة",
                "label": "Neutral"
            },
            {
                "entity": "الكونغرس",
                "label": "Neutral"
            },
            {
                "entity": "الوكالة الدولية للطاقة الذرية",
                "label": "Neutral"
            },
            {
                "entity": "لط",
                "label": "Neutral"
            },
            {
                "entity": "هران",
                "label": "Neutral"
            }
        ],
        "events": [
            {
                "subject": "مشرعين",
                "action": "طلب",
                "object": "تأجيل التصويت",
                "context": "من باراك أوباما",
                "subject_role": "Unknown",
                "object_role": "Unknown"
            },
            {
                "subject": "بوب كروكر",
                "action": "قال",
                "object": "إرجاء نظر",
                "context": "في خطاب مشترك",
                "subject_role": "Antagonist",
                "object_role": "Unknown"
            },
            {
                "subject": "بنجامين كاردين",
                "action": "قال",
                "object": "إرجاء نظر",
                "context": "في خطاب مشترك",
                "subject_role": "Antagonist",
                "object_role": "Unknown"
            },
            {
                "subject": "جون كيري",
                "action": "دافع",
                "object": "مهلة",
                "context": "أمس",
                "subject_role": "Protagonist",
                "object_role": "Unknown"
            },
            {
                "subject": "جون كيري",
                "action": "قال",
                "object": null,
                "context": "أجهزتنا الاستخباراتية مرتاحة",
                "subject_role": "Protagonist",
                "object_role": "Unknown"
            }
        ]
    },
    {
        "text": "شهدت محافظتا إدلب وحلب في شمال سوريا مجزرتين في أول أيام عيد الفطر، نفذهما طيران النظام الحربي والمروحي. كما كثف طيران النظام قصفه على جبهة مدينة الزبداني في ريف دمشق الغربي، بعد أن اضطرت قواته والميليشيات المتحالفة معه إلى التراجع من عدد من المواقع.\n\n وسقط 20 قتيلا على الأقل بينهم عدد من الأطفال في بلدة معرة مصرين شمال شرقي مدينة إدلب، كما سقط 6 قتلى بينهم 4 أطفال في بلدة دارة عزة، و5 قتلى في مدينة الباب في محافظة حلب، مع استمرار المعارك في محيط البلدات الأربع المحاصرة، وهي نبّل والزهراء (في حلب) والفوعة وكفريا (في إدلب).\n\n أما في جبهة الزبداني، غرب العاصمة، فذكر تقرير لناشطين معارضين بعد أسبوعين على بدء الحملة العسكرية في الزبداني أنه سجّل مقتل 34 عنصرا من حزب الله و17 من قوات النظام، بالإضافة إلى عنصرين من الحرس الثوري الإيراني، مقابل سقوط 30 مقاتلا من المعارضة المسلحة في المدينة. وبحسب التقرير، سقط على مدينة الزبداني، منذ بدء المعركة في الثالث من يوليو (تموز) الحالي، 470 برميلا متفجرا وأكثر من 400 صاروخ.\n\n في غضون ذلك، كرّر أحد قياديي حزب الله الدفاع عن خوض ميليشيا الحزب المعارك في الزبداني، معتبرا ذلك خطوة وقائية لمنع الجماعات التي وصفها بالتكفيرية من دخول لبنان. وقال نائب رئيس المجلس التنفيذي في حزب الله نبيل قاووق، خلال إحياء ذكرى أسبوع أحد قتلى حزب الله في جنوب لبنان، إن «معركة الزبداني هي معركة لبنان مائة في المائة، وهي معركة لبنان أولا، لأن المخطط التكفيري كان يريد أن يتخذ من الزبداني منصة للغزو في فصل الصيف باتجاه حام وبريتال ومعربون في البقاع». وأضاف «هم كانوا يحضرون لبدء هذا الغزو باتجاه القرى اللبنانية لتخفيف الضغط عن معركة القلمون وجرود عرسال، وبالتالي فإن المقاومة قامت بواجبها الوطني الاستباقي لمواجهة الخطر القادم من العصابات التكفيرية التي تحتل الزبداني».\n\n وتزامنا مع انقضاء شهر رمضان، أفاد «المرصد السوري لحقوق الإنسان» بأن عدد قتلى النزاع خلال الشهر الفضيل بلغ نحو 5026 قتيلا. وذكر معارضون سوريون أن المدنيين الذين قتلوا نتيجة قصف القوات الحكومية خلال رمضان بلغوا 1452 سوريًا.\n\n ...المزيد",
        "entities": {
            "LOC": [
                "إدلب",
                "وحل",
                "ب",
                "سوريا",
                "الزبداني",
                "دمشق",
                "مع",
                "رة مصرين",
                "دارة عزة",
                "الباب",
                "حلب",
                "نبّل",
                "والز",
                "هر",
                "اء",
                "والف",
                "وعة",
                "وكف",
                "ريا",
                "الزب",
                "داني",
                "لبنان",
                "حام",
                "القلمون",
                "عرسال"
            ],
            "ORG": [
                "حزب الله"
            ],
            "PERS": [
                "نبيل قاووق"
            ]
        },
        "labeled_entities": [
            {
                "entity": "إدلب",
                "label": "Neutral"
            },
            {
                "entity": "وحل",
                "label": "Neutral"
            },
            {
                "entity": "ب",
                "label": "Neutral"
            },
            {
                "entity": "سوريا",
                "label": "Neutral"
            },
            {
                "entity": "الزبداني",
                "label": "Neutral"
            },
            {
                "entity": "دمشق",
                "label": "Neutral"
            },
            {
                "entity": "مع",
                "label": "Neutral"
            },
            {
                "entity": "رة مصرين",
                "label": "Neutral"
            },
            {
                "entity": "دارة عزة",
                "label": "Neutral"
            },
            {
                "entity": "الباب",
                "label": "Neutral"
            },
            {
                "entity": "حلب",
                "label": "Neutral"
            },
            {
                "entity": "نبّل",
                "label": "Neutral"
            },
            {
                "entity": "والز",
                "label": "Neutral"
            },
            {
                "entity": "هر",
                "label": "Neutral"
            },
            {
                "entity": "اء",
                "label": "Neutral"
            },
            {
                "entity": "والف",
                "label": "Neutral"
            },
            {
                "entity": "وعة",
                "label": "Neutral"
            },
            {
                "entity": "وكف",
                "label": "Neutral"
            },
            {
                "entity": "ريا",
                "label": "Neutral"
            },
            {
                "entity": "الزب",
                "label": "Neutral"
            },
            {
                "entity": "داني",
                "label": "Neutral"
            },
            {
                "entity": "لبنان",
                "label": "Neutral"
            },
            {
                "entity": "حام",
                "label": "Neutral"
            },
            {
                "entity": "القلمون",
                "label": "Neutral"
            },
            {
                "entity": "عرسال",
                "label": "Neutral"
            },
            {
                "entity": "حزب الله",
                "label": "Antagonist"
            },
            {
                "entity": "نبيل قاووق",
                "label": "Antagonist"
            }
        ],
        "events": [
            {
                "subject": "طيران النظام",
                "action": "نفذ",
                "object": "مجزرتين",
                "context": "في محافظتا إدلب وحلب في شمال سوريا في أول أيام عيد الفطر",
                "subject_role": "Unknown",
                "object_role": "Unknown"
            },
            {
                "subject": "طيران النظام",
                "action": "كثف",
                "object": "قصفه",
                "context": "على جبهة مدينة الزبداني في ريف دمشق الغربي",
                "subject_role": "Unknown",
                "object_role": "Unknown"
            },
            {
                "subject": "قوات النظام والميليشيات المتحالفة معه",
                "action": "اضطرت",
                "object": "التراجع",
                "context": "من عدد من المواقع في جبهة مدينة الزبداني",
                "subject_role": "Unknown",
                "object_role": "Unknown"
            },
            {
                "subject": "قتلى",
                "action": "سقط",
                "object": "20 قتيلا",
                "context": "على الأقل بينهم عدد من الأطفال في بلدة معرة مصرين شمال شرقي مدينة إدلب",
                "subject_role": "Unknown",
                "object_role": "Unknown"
            },
            {
                "subject": "قتلى",
                "action": "سقط",
                "object": "6 قتلى",
                "context": "بينهم 4 أطفال في بلدة دارة عزة",
                "subject_role": "Unknown",
                "object_role": "Unknown"
            },
            {
                "subject": "قتلى",
                "action": "سقط",
                "object": "5 قتلى",
                "context": "في مدينة الباب في محافظة حلب",
                "subject_role": "Unknown",
                "object_role": "Unknown"
            },
            {
                "subject": "المعارك",
                "action": "استمرار",
                "object": null,
                "context": "في محيط البلدات الأربع المحاصرة، وهي نبّل والزهراء (في حلب) والفوعة وكفريا (في إدلب)",
                "subject_role": "Unknown",
                "object_role": "Unknown"
            },
            {
                "subject": "عناصر من حزب الله وقوات النظام والحرس الثوري الإيراني",
                "action": "قتل",
                "object": "34 عنصرا و 17 عنصرا و عنصرين",
                "context": "في جبهة الزبداني",
                "subject_role": "Unknown",
                "object_role": "Unknown"
            },
            {
                "subject": "مقاتلون من المعارضة المسلحة",
                "action": "سقط",
                "object": "30 مقاتلا",
                "context": "في المدينة (الزبداني)",
                "subject_role": "Unknown",
                "object_role": "Unknown"
            },
            {
                "subject": "برميلا متفجرا وصواريخ",
                "action": "سقط",
                "object": "470 برميلا و 400 صاروخ",
                "context": "على مدينة الزبداني، منذ بدء المعركة في الثالث من يوليو (تموز) الحالي",
                "subject_role": "Unknown",
                "object_role": "Unknown"
            },
            {
                "subject": "قياديي حزب الله",
                "action": "كرر",
                "object": "الدفاع",
                "context": "عن خوض ميليشيا الحزب المعارك في الزبداني",
                "subject_role": "Antagonist",
                "object_role": "Neutral"
            },
            {
                "subject": "نبيل قاووق",
                "action": "قال",
                "object": null,
                "context": "إن «معركة الزبداني هي معركة لبنان مائة في المائة",
                "subject_role": "Antagonist",
                "object_role": "Unknown"
            },
            {
                "subject": "المقاومة",
                "action": "قامت",
                "object": "واجبها",
                "context": "الوطني الاستباقي لمواجهة الخطر القادم من العصابات التكفيرية التي تحتل الزبداني",
                "subject_role": "Unknown",
                "object_role": "Unknown"
            },
            {
                "subject": "قتلى النزاع",
                "action": "بلغ",
                "object": "5026 قتيلا",
                "context": "خلال شهر رمضان",
                "subject_role": "Unknown",
                "object_role": "Unknown"
            },
            {
                "subject": "المدنيين",
                "action": "قتل",
                "object": "1452 سوريا",
                "context": "نتيجة قصف القوات الحكومية خلال رمضان",
                "subject_role": "Neutral",
                "object_role": "Neutral"
            }
        ]
    },
    {
        "text": "بينما تضاربت الأنباء حول دواعي توقف معارك الأنبار، بعد التقدم الذي حققته القوات العراقية باتجاه مدينتي الرمادي والفلوجة كبرى مدن محافظة الأنبار، علمت «الشرق الأوسط» من مصدر أمني مسؤول أن «توقف المعارك جاء إثر نصيحة أميركية مفادها أن تنظيم داعش انسحب كثيرا من أجل التمركز بين السكان في المدن لتحقيق هدفين؛ الأول هو اكتمال وصول تعزيزاته من المناطق الأخرى لا سيما الموصل وسوريا، والثاني هو عرقلة أي تقدم للقوات العراقية بسبب وجود أعداد كبيرة من المدنيين في الفلوجة تحديدا».\n\n وأضاف المصدر الذي طلب عدم الإشارة إلى اسمه أن «الجانب الأميركي يتولى من خلال الطلعات الجوية قطع إمدادات (داعش)، لكنه يواجه تكتيكا جديدا بات يستخدمه التنظيم ويتمثل في جلب إمدادات بسيارات مدنية تتكون من سيارة أو سيارتين، وغالبا ما تحمل بعض المدنيين بمن فيهم الأطفال والنساء لكي لا يتم استهدافها من قبل الطيران».\n\n من ناحية أخرى، اعتقل تنظيم داعش 38 مواطنا في مناطق مختلفة بمدينة الموصل أمس، إثر أدائهم صلاة العيد التي منعها التنظيم قبل أيام. وقال سعيد مموزيني، مسؤول إعلام الحزب الديمقراطي الكردستاني في الموصل، لـ«الشرق الأوسط»: «رغم منع التنظيم لمراسم صلاة العيد في الموصل، فإن مواطني المدينة تحدوا التنظيم وأقاموا صلاة عيد الفطر في عدد من مساجدها، الأمر الذي دفع بالتنظيم إلى شن حملة اعتقالات واسعة في صفوف المصلين أسفرت عن اعتقال 38 مواطنا موصليا.\n\n وبحسب المعلومات الواردة إلينا ساق (داعش) المعتقلين إلى جهة مجهولة، ولم يتبين حتى الآن مصيرهم». وأضاف مموزيني: «اندلعت اشتباكات بين مواطنين من الموصل ومسلحي (داعش) في مقبرة وادي عقاب (غرب الموصل)، جراء منع التنظيم المواطنين من زيارة قبور موتاهم، وأطلق مسلحو (داعش) النار على المواطنين فقتلوا اثنين منهم وأصابوا عشرة آخرين بجروح، فيما جرح ثلاثة مسلحين»، مشيرًا إلى أن المواطنين ردوا على مسلحي «داعش» بالحجارة.\n\n ...المزيد",
        "entities": {
            "LOC": [
                "الأنبار",
                "الرمادي",
                "والف",
                "لوجة",
                "الموصل",
                "وسوريا",
                "الفلوجة",
                "وادي عقاب"
            ],
            "ORG": [
                "الشرق الأوسط",
                "داعش"
            ],
            "PERS": [
                "سعيد مموزيني",
                "مم",
                "وزي",
                "ني"
            ]
        },
        "labeled_entities": [
            {
                "entity": "الأنبار",
                "label": "Neutral"
            },
            {
                "entity": "الرمادي",
                "label": "Neutral"
            },
            {
                "entity": "والف",
                "label": "Neutral"
            },
            {
                "entity": "لوجة",
                "label": "Neutral"
            },
            {
                "entity": "الموصل",
                "label": "Neutral"
            },
            {
                "entity": "وسوريا",
                "label": "Neutral"
            },
            {
                "entity": "الفلوجة",
                "label": "Neutral"
            },
            {
                "entity": "وادي عقاب",
                "label": "Neutral"
            },
            {
                "entity": "الشرق الأوسط",
                "label": "Neutral"
            },
            {
                "entity": "داعش",
                "label": "Antagonist"
            },
            {
                "entity": "سعيد مموزيني",
                "label": "Neutral"
            },
            {
                "entity": "مم",
                "label": "Neutral"
            },
            {
                "entity": "وزي",
                "label": "Neutral"
            },
            {
                "entity": "ني",
                "label": "Neutral"
            }
        ],
        "events": [
            {
                "subject": "معارك الأنبار",
                "action": "توقف",
                "context": "بعد التقدم الذي حققته القوات العراقية باتجاه مدينتي الرمادي والفلوجة",
                "subject_role": "Neutral",
                "object_role": "Unknown"
            },
            {
                "subject": "تنظيم داعش",
                "action": "انسحب",
                "object": "كثيرا",
                "context": "من أجل التمركز بين السكان في المدن لتحقيق هدفين",
                "subject_role": "Unknown",
                "object_role": "Unknown"
            },
            {
                "subject": "الجانب الأميركي",
                "action": "يتولى",
                "object": "قطع إمدادات (داعش)",
                "context": "من خلال الطلعات الجوية",
                "subject_role": "Unknown",
                "object_role": "Unknown"
            },
            {
                "subject": "تنظيم داعش",
                "action": "يستخدم",
                "object": "تكتيكا جديدا",
                "context": "يتمثل في جلب إمدادات بسيارات مدنية",
                "subject_role": "Unknown",
                "object_role": "Unknown"
            },
            {
                "subject": "تنظيم داعش",
                "action": "اعتقل",
                "object": "38 مواطنا",
                "context": "في مناطق مختلفة بمدينة الموصل أمس، إثر أدائهم صلاة العيد التي منعها التنظيم قبل أيام",
                "subject_role": "Unknown",
                "object_role": "Unknown"
            },
            {
                "subject": "التنظيم",
                "action": "منع",
                "object": "مراسم صلاة العيد",
                "context": "في الموصل",
                "subject_role": "Unknown",
                "object_role": "Unknown"
            },
            {
                "subject": "مواطني المدينة",
                "action": "تحدوا",
                "object": "التنظيم",
                "context": "وأقاموا صلاة عيد الفطر في عدد من مساجدها",
                "subject_role": "Unknown",
                "object_role": "Unknown"
            },
            {
                "subject": "التنظيم",
                "action": "شن",
                "object": "حملة اعتقالات واسعة",
                "context": "في صفوف المصلين أسفرت عن اعتقال 38 مواطنا موصليا",
                "subject_role": "Unknown",
                "object_role": "Unknown"
            },
            {
                "subject": "داعش",
                "action": "ساق",
                "object": "المعتقلين",
                "context": "إلى جهة مجهولة",
                "subject_role": "Antagonist",
                "object_role": "Unknown"
            },
            {
                "subject": "اشتباكات",
                "action": "اندلعت",
                "context": "بين مواطنين من الموصل ومسلحي (داعش) في مقبرة وادي عقاب",
                "subject_role": "Unknown",
                "object_role": "Unknown"
            },
            {
                "subject": "التنظيم",
                "action": "منع",
                "object": "المواطنين",
                "context": "من زيارة قبور موتاهم",
                "subject_role": "Unknown",
                "object_role": "Neutral"
            },
            {
                "subject": "مسلحو (داعش)",
                "action": "أطلقوا النار",
                "object": "على المواطنين",
                "context": "فقتلوا اثنين منهم وأصابوا عشرة آخرين بجروح",
                "subject_role": "Unknown",
                "object_role": "Unknown"
            },
            {
                "subject": "المواطنين",
                "action": "ردوا",
                "object": "على مسلحي «داعش»",
                "context": "بالحجارة",
                "subject_role": "Neutral",
                "object_role": "Unknown"
            }
        ]
    }
]